{
  "Alabama":{
    "#":"14",
    "Total Cases":"164,526",
    "New Cases":"+1,061",
    "Total Deaths":"2,664",
    "New Deaths":"+11",
    "Total Recovered":"71,240",
    "Active Cases":"90,622",
    "Tot Cases\/ 1M pop":"33,555",
    "Deaths\/ 1M pop":"543",
    "Total Tests":"1,264,481",
    "Tests\/  1M pop ":"257,890",
    "Population":"4,903,185",
    "Source":"[1]",
    "Projections":"[projections]"
  },
  "Alaska":{
    "#":"47",
    "Total Cases":"9,431",
    "New Cases":"+249",
    "Total Deaths":"60",
    "New Deaths":0,
    "Total Recovered":"5,136",
    "Active Cases":"4,235",
    "Tot Cases\/ 1M pop":"12,892",
    "Deaths\/ 1M pop":"82",
    "Total Tests":"499,253",
    "Tests\/  1M pop ":"682,464",
    "Population":"731,545",
    "Source":"[1]",
    "Projections":"[projections]"
  },
  "Arizona":{
    "#":"8",
    "Total Cases":"224,978",
    "New Cases":"+894",
    "Total Deaths":"5,759",
    "New Deaths":"+13",
    "Total Recovered":"36,723",
    "Active Cases":"182,496",
    "Tot Cases\/ 1M pop":"30,909",
    "Deaths\/ 1M pop":"791",
    "Total Tests":"1,856,872",
    "Tests\/  1M pop ":"255,110",
    "Population":"7,278,717",
    "Source":"[1]",
    "Projections":"[projections]"
  },
  "Arkansas":{
    "#":"28",
    "Total Cases":"92,220",
    "New Cases":"+908",
    "Total Deaths":"1,552",
    "New Deaths":"+22",
    "Total Recovered":"82,924",
    "Active Cases":"7,744",
    "Tot Cases\/ 1M pop":"30,559",
    "Deaths\/ 1M pop":"514",
    "Total Tests":"1,156,803",
    "Tests\/  1M pop ":"383,326",
    "Population":"3,017,804",
    "Source":"[1]\u00a0[2]\u00a0[3]\u00a0[4]\u00a0[5]",
    "Projections":"[projections]"
  },
  "California":{
    "#":"1",
    "Total Cases":"851,328",
    "New Cases":"+1,776",
    "Total Deaths":"16,548",
    "New Deaths":"+39",
    "Total Recovered":"438,455",
    "Active Cases":"396,325",
    "Tot Cases\/ 1M pop":"21,546",
    "Deaths\/ 1M pop":"419",
    "Total Tests":"15,878,445",
    "Tests\/  1M pop ":"401,862",
    "Population":"39,512,223",
    "Source":"[view by county]\u00a0[1]",
    "Projections":"[projections]"
  },
  "Colorado":{
    "#":"32",
    "Total Cases":"77,642",
    "New Cases":"+1,023",
    "Total Deaths":"2,112",
    "New Deaths":"+9",
    "Total Recovered":"35,114",
    "Active Cases":"40,416",
    "Tot Cases\/ 1M pop":"13,482",
    "Deaths\/ 1M pop":"367",
    "Total Tests":"1,006,847",
    "Tests\/  1M pop ":"174,838",
    "Population":"5,758,736",
    "Source":"[1]",
    "Projections":"[projections]"
  },
  "Connecticut":{
    "#":"34",
    "Total Cases":"60,038",
    "New Cases":0,
    "Total Deaths":"4,530",
    "New Deaths":0,
    "Total Recovered":"42,954",
    "Active Cases":"12,554",
    "Tot Cases\/ 1M pop":"16,840",
    "Deaths\/ 1M pop":"1,271",
    "Total Tests":"1,794,099",
    "Tests\/  1M pop ":"503,213",
    "Population":"3,565,287",
    "Source":"[1]\u00a0[2]",
    "Projections":"[projections]"
  },
  "Delaware":{
    "#":"42",
    "Total Cases":"21,998",
    "New Cases":"+171",
    "Total Deaths":"653",
    "New Deaths":"+2",
    "Total Recovered":"11,338",
    "Active Cases":"10,007",
    "Tot Cases\/ 1M pop":"22,591",
    "Deaths\/ 1M pop":"671",
    "Total Tests":"306,564",
    "Tests\/  1M pop ":"314,824",
    "Population":"973,764",
    "Source":"[1]",
    "Projections":"[projections]"
  },
  "District Of Columbia":{
    "#":"45",
    "Total Cases":"15,918",
    "New Cases":"+75",
    "Total Deaths":"636",
    "New Deaths":"+2",
    "Total Recovered":"12,492",
    "Active Cases":"2,790",
    "Tot Cases\/ 1M pop":"22,555",
    "Deaths\/ 1M pop":"901",
    "Total Tests":"429,099",
    "Tests\/  1M pop ":"608,005",
    "Population":"705,749",
    "Source":"[1]",
    "Projections":"[projections]"
  },
  "Florida":{
    "#":"3",
    "Total Cases":"728,921",
    "New Cases":0,
    "Total Deaths":"15,187",
    "New Deaths":0,
    "Total Recovered":"416,967",
    "Active Cases":"296,767",
    "Tot Cases\/ 1M pop":"33,938",
    "Deaths\/ 1M pop":"707",
    "Total Tests":"5,525,411",
    "Tests\/  1M pop ":"257,262",
    "Population":"21,477,737",
    "Source":"[view by county]\u00a0[1]\u00a0[2]\u00a0[3]",
    "Projections":"[projections]"
  },
  "Georgia":{
    "#":"5",
    "Total Cases":"330,269",
    "New Cases":"+1,237",
    "Total Deaths":"7,393",
    "New Deaths":"+45",
    "Total Recovered":"131,066",
    "Active Cases":"191,810",
    "Tot Cases\/ 1M pop":"31,106",
    "Deaths\/ 1M pop":"696",
    "Total Tests":"3,442,732",
    "Tests\/  1M pop ":"324,253",
    "Population":"10,617,423",
    "Source":"[1]",
    "Projections":"[projections]"
  },
  "Hawaii":{
    "#":"46",
    "Total Cases":"13,371",
    "New Cases":"+71",
    "Total Deaths":"168",
    "New Deaths":"+2",
    "Total Recovered":"10,713",
    "Active Cases":"2,490",
    "Tot Cases\/ 1M pop":"9,444",
    "Deaths\/ 1M pop":"119",
    "Total Tests":"450,894",
    "Tests\/  1M pop ":"318,457",
    "Population":"1,415,872",
    "Source":"[1]\u00a0[2]\u00a0[3]\u00a0[4]",
    "Projections":"[projections]"
  },
  "Idaho":{
    "#":"36",
    "Total Cases":"47,701",
    "New Cases":"+613",
    "Total Deaths":"507",
    "New Deaths":"+1",
    "Total Recovered":"24,089",
    "Active Cases":"23,105",
    "Tot Cases\/ 1M pop":"26,692",
    "Deaths\/ 1M pop":"284",
    "Total Tests":"333,839",
    "Tests\/  1M pop ":"186,809",
    "Population":"1,787,065",
    "Source":"[1]\u00a0[2]\u00a0[3]",
    "Projections":"[projections]"
  },
  "Illinois":{
    "#":"6",
    "Total Cases":"319,461",
    "New Cases":"+2,905",
    "Total Deaths":"9,221",
    "New Deaths":"+30",
    "Total Recovered":"214,680",
    "Active Cases":"95,560",
    "Tot Cases\/ 1M pop":"25,210",
    "Deaths\/ 1M pop":"728",
    "Total Tests":"6,243,635",
    "Tests\/  1M pop ":"492,718",
    "Population":"12,671,821",
    "Source":"[1]\u00a0[2]\u00a0[3]\u00a0[4]",
    "Projections":"[projections]"
  },
  "Indiana":{
    "#":"21",
    "Total Cases":"133,411",
    "New Cases":"+1,918",
    "Total Deaths":"3,782",
    "New Deaths":"+21",
    "Total Recovered":"101,184",
    "Active Cases":"28,445",
    "Tot Cases\/ 1M pop":"19,817",
    "Deaths\/ 1M pop":"562",
    "Total Tests":"2,306,562",
    "Tests\/  1M pop ":"342,615",
    "Population":"6,732,219",
    "Source":"[1]\u00a0[2]",
    "Projections":"[projections]"
  },
  "Iowa":{
    "#":"26",
    "Total Cases":"98,588",
    "New Cases":"+1,113",
    "Total Deaths":"1,455",
    "New Deaths":"+14",
    "Total Recovered":"75,949",
    "Active Cases":"21,184",
    "Tot Cases\/ 1M pop":"31,247",
    "Deaths\/ 1M pop":"461",
    "Total Tests":"856,937",
    "Tests\/  1M pop ":"271,606",
    "Population":"3,155,070",
    "Source":"[1]\u00a0[2]",
    "Projections":"[projections]"
  },
  "Kansas":{
    "#":"33",
    "Total Cases":"67,061",
    "New Cases":"+180",
    "Total Deaths":"775",
    "New Deaths":"+12",
    "Total Recovered":"51,828",
    "Active Cases":"14,458",
    "Tot Cases\/ 1M pop":"23,019",
    "Deaths\/ 1M pop":"266",
    "Total Tests":"560,189",
    "Tests\/  1M pop ":"192,286",
    "Population":"2,913,314",
    "Source":"[1]\u00a0[2]\u00a0[3]\u00a0[4]\u00a0[5]\u00a0[6]\u00a0[7]\u00a0[8]\u00a0[9]",
    "Projections":"[projections]"
  },
  "Kentucky":{
    "#":"31",
    "Total Cases":"79,445",
    "New Cases":"+989",
    "Total Deaths":"1,249",
    "New Deaths":"+7",
    "Total Recovered":"13,539",
    "Active Cases":"64,657",
    "Tot Cases\/ 1M pop":"17,782",
    "Deaths\/ 1M pop":"280",
    "Total Tests":"1,650,148",
    "Tests\/  1M pop ":"369,353",
    "Population":"4,467,673",
    "Source":"[1]\u00a0[2]\u00a0[3]",
    "Projections":"[projections]"
  },
  "Louisiana":{
    "#":"12",
    "Total Cases":"170,878",
    "New Cases":0,
    "Total Deaths":"5,635",
    "New Deaths":0,
    "Total Recovered":"157,873",
    "Active Cases":"7,370",
    "Tot Cases\/ 1M pop":"36,757",
    "Deaths\/ 1M pop":"1,212",
    "Total Tests":"2,447,559",
    "Tests\/  1M pop ":"526,493",
    "Population":"4,648,794",
    "Source":"[view by county]\u00a0[1]",
    "Projections":"[projections]"
  },
  "Maine":{
    "#":"50",
    "Total Cases":"5,696",
    "New Cases":"+30",
    "Total Deaths":"143",
    "New Deaths":0,
    "Total Recovered":"4,951",
    "Active Cases":"602",
    "Tot Cases\/ 1M pop":"4,237",
    "Deaths\/ 1M pop":"106",
    "Total Tests":"501,020",
    "Tests\/  1M pop ":"372,724",
    "Population":"1,344,212",
    "Source":"[1]\u00a0[2]",
    "Projections":"[projections]"
  },
  "Maryland":{
    "#":"22",
    "Total Cases":"130,795",
    "New Cases":"+636",
    "Total Deaths":"3,995",
    "New Deaths":"+5",
    "Total Recovered":"7,721",
    "Active Cases":"119,079",
    "Tot Cases\/ 1M pop":"21,634",
    "Deaths\/ 1M pop":"661",
    "Total Tests":"2,863,083",
    "Tests\/  1M pop ":"473,575",
    "Population":"6,045,680",
    "Source":"[1]",
    "Projections":"[projections]"
  },
  "Massachusetts":{
    "#":"20",
    "Total Cases":"138,340",
    "New Cases":"+639",
    "Total Deaths":"9,587",
    "New Deaths":"+10",
    "Total Recovered":"116,364",
    "Active Cases":"12,389",
    "Tot Cases\/ 1M pop":"20,071",
    "Deaths\/ 1M pop":"1,391",
    "Total Tests":"2,667,773",
    "Tests\/  1M pop ":"387,054",
    "Population":"6,892,503",
    "Source":"[1]",
    "Projections":"[projections]"
  },
  "Michigan":{
    "#":"17",
    "Total Cases":"149,464",
    "New Cases":"+1,648",
    "Total Deaths":"7,219",
    "New Deaths":"+19",
    "Total Recovered":"99,521",
    "Active Cases":"42,724",
    "Tot Cases\/ 1M pop":"14,966",
    "Deaths\/ 1M pop":"723",
    "Total Tests":"4,353,346",
    "Tests\/  1M pop ":"435,908",
    "Population":"9,986,857",
    "Source":"[1]\u00a0[2]\u00a0[3]\u00a0[4]",
    "Projections":"[projections]"
  },
  "Minnesota":{
    "#":"23",
    "Total Cases":"110,828",
    "New Cases":"+1,516",
    "Total Deaths":"2,184",
    "New Deaths":"+10",
    "Total Recovered":"99,054",
    "Active Cases":"9,590",
    "Tot Cases\/ 1M pop":"19,652",
    "Deaths\/ 1M pop":"387",
    "Total Tests":"2,288,662",
    "Tests\/  1M pop ":"405,818",
    "Population":"5,639,632",
    "Source":"[1]\u00a0[2]",
    "Projections":"[projections]"
  },
  "Mississippi":{
    "#":"24",
    "Total Cases":"104,638",
    "New Cases":"+957",
    "Total Deaths":"3,096",
    "New Deaths":"+16",
    "Total Recovered":"90,577",
    "Active Cases":"10,965",
    "Tot Cases\/ 1M pop":"35,159",
    "Deaths\/ 1M pop":"1,040",
    "Total Tests":"904,005",
    "Tests\/  1M pop ":"303,750",
    "Population":"2,976,149",
    "Source":"[1]\u00a0[2]\u00a0[3]",
    "Projections":"[projections]"
  },
  "Missouri":{
    "#":"18",
    "Total Cases":"149,148",
    "New Cases":"+2,394",
    "Total Deaths":"2,512",
    "New Deaths":"+27",
    "Total Recovered":"27,766",
    "Active Cases":"118,870",
    "Tot Cases\/ 1M pop":"24,301",
    "Deaths\/ 1M pop":"409",
    "Total Tests":"2,098,950",
    "Tests\/  1M pop ":"341,992",
    "Population":"6,137,428",
    "Source":"[1]\u00a0[2]\u00a0[3]\u00a0[4]\u00a0[5]\u00a0[6]\u00a0[7]\u00a0[8]",
    "Projections":"[projections]"
  },
  "Montana":{
    "#":"43",
    "Total Cases":"18,117",
    "New Cases":"+718",
    "Total Deaths":"209",
    "New Deaths":"+3",
    "Total Recovered":"11,361",
    "Active Cases":"6,547",
    "Tot Cases\/ 1M pop":"16,951",
    "Deaths\/ 1M pop":"196",
    "Total Tests":"388,649",
    "Tests\/  1M pop ":"363,639",
    "Population":"1,068,778",
    "Source":"[1]\u00a0[2]\u00a0[3]\u00a0[4]",
    "Projections":"[projections]"
  },
  "Nebraska":{
    "#":"35",
    "Total Cases":"51,144",
    "New Cases":"+1,085",
    "Total Deaths":"519",
    "New Deaths":"+5",
    "Total Recovered":"36,091",
    "Active Cases":"14,534",
    "Tot Cases\/ 1M pop":"26,439",
    "Deaths\/ 1M pop":"268",
    "Total Tests":"504,746",
    "Tests\/  1M pop ":"260,930",
    "Population":"1,934,408",
    "Source":"[1]\u00a0[2]",
    "Projections":"[projections]"
  },
  "Nevada":{
    "#":"29",
    "Total Cases":"85,399",
    "New Cases":"+806",
    "Total Deaths":"1,659",
    "New Deaths":"+2",
    "Total Recovered":"63,045",
    "Active Cases":"20,695",
    "Tot Cases\/ 1M pop":"27,726",
    "Deaths\/ 1M pop":"539",
    "Total Tests":"1,128,337",
    "Tests\/  1M pop ":"366,325",
    "Population":"3,080,156",
    "Source":"[1]\u00a0[2]",
    "Projections":"[projections]"
  },
  "New Hampshire":{
    "#":"48",
    "Total Cases":"9,092",
    "New Cases":"+122",
    "Total Deaths":"455",
    "New Deaths":"+5",
    "Total Recovered":"7,945",
    "Active Cases":"692",
    "Tot Cases\/ 1M pop":"6,687",
    "Deaths\/ 1M pop":"335",
    "Total Tests":"323,954",
    "Tests\/  1M pop ":"238,252",
    "Population":"1,359,711",
    "Source":"[1]\u00a0[2]",
    "Projections":"[projections]"
  },
  "New Jersey":{
    "#":"9",
    "Total Cases":"216,697",
    "New Cases":"+754",
    "Total Deaths":"16,290",
    "New Deaths":"+7",
    "Total Recovered":"175,221",
    "Active Cases":"25,186",
    "Tot Cases\/ 1M pop":"24,397",
    "Deaths\/ 1M pop":"1,834",
    "Total Tests":"3,914,021",
    "Tests\/  1M pop ":"440,659",
    "Population":"8,882,190",
    "Source":"[view by county]\u00a0[1]",
    "Projections":"[projections]"
  },
  "New Mexico":{
    "#":"38",
    "Total Cases":"32,722",
    "New Cases":"+481",
    "Total Deaths":"907",
    "New Deaths":"+5",
    "Total Recovered":"18,621",
    "Active Cases":"13,194",
    "Tot Cases\/ 1M pop":"15,605",
    "Deaths\/ 1M pop":"433",
    "Total Tests":"989,652",
    "Tests\/  1M pop ":"471,976",
    "Population":"2,096,829",
    "Source":"[1]\u00a0[2]",
    "Projections":"[projections]"
  },
  "New York":{
    "#":"4",
    "Total Cases":"508,307",
    "New Cases":"+1,417",
    "Total Deaths":"33,377",
    "New Deaths":"+6",
    "Total Recovered":"403,759",
    "Active Cases":"71,171",
    "Tot Cases\/ 1M pop":"26,129",
    "Deaths\/ 1M pop":"1,716",
    "Total Tests":"11,921,319",
    "Tests\/  1M pop ":"612,809",
    "Population":"19,453,561",
    "Source":"[view by county]\u00a0[1]\u00a0[2]\u00a0[3]",
    "Projections":"[projections]"
  },
  "North Carolina":{
    "#":"7",
    "Total Cases":"229,752",
    "New Cases":"+2,321",
    "Total Deaths":"3,765",
    "New Deaths":"+18",
    "Total Recovered":"192,644",
    "Active Cases":"33,343",
    "Tot Cases\/ 1M pop":"21,906",
    "Deaths\/ 1M pop":"359",
    "Total Tests":"3,344,152",
    "Tests\/  1M pop ":"318,853",
    "Population":"10,488,084",
    "Source":"[1]\u00a0[2]\u00a0[3]",
    "Projections":"[projections]"
  },
  "North Dakota":{
    "#":"40",
    "Total Cases":"26,628",
    "New Cases":"+588",
    "Total Deaths":"336",
    "New Deaths":"+15",
    "Total Recovered":"22,123",
    "Active Cases":"4,169",
    "Tot Cases\/ 1M pop":"34,942",
    "Deaths\/ 1M pop":"441",
    "Total Tests":"257,186",
    "Tests\/  1M pop ":"337,487",
    "Population":"762,062",
    "Source":"[1]\u00a0[2]",
    "Projections":"[projections]"
  },
  "Ohio":{
    "#":"13",
    "Total Cases":"167,480",
    "New Cases":"+1,334",
    "Total Deaths":"5,004",
    "New Deaths":"+4",
    "Total Recovered":"142,479",
    "Active Cases":"19,997",
    "Tot Cases\/ 1M pop":"14,328",
    "Deaths\/ 1M pop":"428",
    "Total Tests":"3,574,163",
    "Tests\/  1M pop ":"305,769",
    "Population":"11,689,100",
    "Source":"[view by county]\u00a0[1]\u00a0[2]\u00a0[3]",
    "Projections":"[projections]"
  },
  "Oklahoma":{
    "#":"25",
    "Total Cases":"98,621",
    "New Cases":"+1,533",
    "Total Deaths":"1,095",
    "New Deaths":"+4",
    "Total Recovered":"83,633",
    "Active Cases":"13,893",
    "Tot Cases\/ 1M pop":"24,923",
    "Deaths\/ 1M pop":"277",
    "Total Tests":"1,353,634",
    "Tests\/  1M pop ":"342,088",
    "Population":"3,956,971",
    "Source":"[1]\u00a0[2]",
    "Projections":"[projections]"
  },
  "Oregon":{
    "#":"37",
    "Total Cases":"36,924",
    "New Cases":"+398",
    "Total Deaths":"599",
    "New Deaths":"+2",
    "Total Recovered":"5,901",
    "Active Cases":"30,424",
    "Tot Cases\/ 1M pop":"8,754",
    "Deaths\/ 1M pop":"142",
    "Total Tests":"736,587",
    "Tests\/  1M pop ":"174,640",
    "Population":"4,217,737",
    "Source":"[1]\u00a0[2]\u00a0[3]",
    "Projections":"[projections]"
  },
  "Pennsylvania":{
    "#":"11",
    "Total Cases":"175,804",
    "New Cases":"+1,452",
    "Total Deaths":"8,427",
    "New Deaths":"+33",
    "Total Recovered":"137,139",
    "Active Cases":"30,238",
    "Tot Cases\/ 1M pop":"13,733",
    "Deaths\/ 1M pop":"658",
    "Total Tests":"2,300,177",
    "Tests\/  1M pop ":"179,673",
    "Population":"12,801,989",
    "Source":"[view by county]\u00a0[1]",
    "Projections":"[projections]"
  },
  "Rhode Island":{
    "#":"41",
    "Total Cases":"26,294",
    "New Cases":0,
    "Total Deaths":"1,130",
    "New Deaths":0,
    "Total Recovered":"2,422",
    "Active Cases":"22,742",
    "Tot Cases\/ 1M pop":"24,821",
    "Deaths\/ 1M pop":"1,067",
    "Total Tests":"864,638",
    "Tests\/  1M pop ":"816,188",
    "Population":"1,059,361",
    "Source":"[1]\u00a0[2]",
    "Projections":"[projections]"
  },
  "South Carolina":{
    "#":"16",
    "Total Cases":"156,621",
    "New Cases":"+945",
    "Total Deaths":"3,551",
    "New Deaths":"+21",
    "Total Recovered":"77,102",
    "Active Cases":"75,968",
    "Tot Cases\/ 1M pop":"30,419",
    "Deaths\/ 1M pop":"690",
    "Total Tests":"1,611,221",
    "Tests\/  1M pop ":"312,937",
    "Population":"5,148,714",
    "Source":"[1]\u00a0[2]\u00a0[3]",
    "Projections":"[projections]"
  },
  "South Dakota":{
    "#":"39",
    "Total Cases":"27,947",
    "New Cases":"+732",
    "Total Deaths":"286",
    "New Deaths":"+9",
    "Total Recovered":"22,128",
    "Active Cases":"5,533",
    "Tot Cases\/ 1M pop":"31,591",
    "Deaths\/ 1M pop":"323",
    "Total Tests":"216,485",
    "Tests\/  1M pop ":"244,710",
    "Population":"884,659",
    "Source":"[1]",
    "Projections":"[projections]"
  },
  "Tennessee":{
    "#":"10",
    "Total Cases":"212,649",
    "New Cases":"+1,646",
    "Total Deaths":"2,758",
    "New Deaths":"+26",
    "Total Recovered":"191,651",
    "Active Cases":"18,240",
    "Tot Cases\/ 1M pop":"31,138",
    "Deaths\/ 1M pop":"404",
    "Total Tests":"3,131,539",
    "Tests\/  1M pop ":"458,553",
    "Population":"6,829,174",
    "Source":"[1]\u00a0[2]\u00a0[3]",
    "Projections":"[projections]"
  },
  "Texas":{
    "#":"2",
    "Total Cases":"832,436",
    "New Cases":"+2,832",
    "Total Deaths":"17,055",
    "New Deaths":"+63",
    "Total Recovered":"718,115",
    "Active Cases":"97,266",
    "Tot Cases\/ 1M pop":"28,709",
    "Deaths\/ 1M pop":"588",
    "Total Tests":"7,420,113",
    "Tests\/  1M pop ":"255,902",
    "Population":"28,995,881",
    "Source":"[view by county]\u00a0[1]\u00a0[2]",
    "Projections":"[projections]"
  },
  "Utah":{
    "#":"30",
    "Total Cases":"84,644",
    "New Cases":"+1,354",
    "Total Deaths":"510",
    "New Deaths":"+5",
    "Total Recovered":"62,401",
    "Active Cases":"21,733",
    "Tot Cases\/ 1M pop":"26,402",
    "Deaths\/ 1M pop":"159",
    "Total Tests":"1,203,445",
    "Tests\/  1M pop ":"375,378",
    "Population":"3,205,958",
    "Source":"[1]",
    "Projections":"[projections]"
  },
  "Vermont":{
    "#":"51",
    "Total Cases":"1,857",
    "New Cases":"+11",
    "Total Deaths":"58",
    "New Deaths":0,
    "Total Recovered":"1,651",
    "Active Cases":"148",
    "Tot Cases\/ 1M pop":"2,976",
    "Deaths\/ 1M pop":"93",
    "Total Tests":"171,179",
    "Tests\/  1M pop ":"274,330",
    "Population":"623,989",
    "Source":"[1]",
    "Projections":"[projections]"
  },
  "Virginia":{
    "#":"15",
    "Total Cases":"157,905",
    "New Cases":"+1,256",
    "Total Deaths":"3,354",
    "New Deaths":"+10",
    "Total Recovered":"18,336",
    "Active Cases":"136,215",
    "Tot Cases\/ 1M pop":"18,500",
    "Deaths\/ 1M pop":"393",
    "Total Tests":"2,410,672",
    "Tests\/  1M pop ":"282,428",
    "Population":"8,535,519",
    "Source":"[1]\u00a0[2]",
    "Projections":"[projections]"
  },
  "Washington":{
    "#":"27",
    "Total Cases":"95,932",
    "New Cases":"+293",
    "Total Deaths":"2,193",
    "New Deaths":0,
    "Total Recovered":"45,086",
    "Active Cases":"48,653",
    "Tot Cases\/ 1M pop":"12,598",
    "Deaths\/ 1M pop":"288",
    "Total Tests":"2,061,438",
    "Tests\/  1M pop ":"270,711",
    "Population":"7,614,893",
    "Source":"[view by county]\u00a0[1]",
    "Projections":"[projections]"
  },
  "West Virginia":{
    "#":"44",
    "Total Cases":"17,913",
    "New Cases":"+206",
    "Total Deaths":"381",
    "New Deaths":"+5",
    "Total Recovered":"13,086",
    "Active Cases":"4,446",
    "Tot Cases\/ 1M pop":"9,995",
    "Deaths\/ 1M pop":"213",
    "Total Tests":"627,403",
    "Tests\/  1M pop ":"350,085",
    "Population":"1,792,147",
    "Source":"[1]",
    "Projections":"[projections]"
  },
  "Wisconsin":{
    "#":"19",
    "Total Cases":"147,560",
    "New Cases":"+2,742",
    "Total Deaths":"1,458",
    "New Deaths":"+18",
    "Total Recovered":"117,865",
    "Active Cases":"28,237",
    "Tot Cases\/ 1M pop":"25,343",
    "Deaths\/ 1M pop":"250",
    "Total Tests":"1,677,866",
    "Tests\/  1M pop ":"288,173",
    "Population":"5,822,434",
    "Source":"[1]\u00a0[2]\u00a0[3]\u00a0[4]\u00a0[5]\u00a0[6]",
    "Projections":"[projections]"
  },
  "Wyoming":{
    "#":"49",
    "Total Cases":"7,455",
    "New Cases":"+120",
    "Total Deaths":"54",
    "New Deaths":0,
    "Total Recovered":"5,807",
    "Active Cases":"1,594",
    "Tot Cases\/ 1M pop":"12,881",
    "Deaths\/ 1M pop":"93",
    "Total Tests":"188,406",
    "Tests\/  1M pop ":"325,534",
    "Population":"578,759",
    "Source":"[1]\u00a0[2]",
    "Projections":"[projections]"
  }
}