{
  "Alabama":{
    "#":"14",
    "Total Cases":"125,235",
    "New Cases":"+1,346",
    "Total Deaths":"2,162",
    "New Deaths":"+10",
    "Total Recovered":"48,028",
    "Active Cases":"75,045",
    "Tot Cases\/ 1M pop":"25,542",
    "Deaths\/ 1M pop":"441",
    "Total Tests":"972,283",
    "Tests\/  1M pop ":"198,296",
    "Population":"4,903,185",
    "Source":"[1]",
    "Projections":"[projections]"
  },
  "Alaska":{
    "#":"53",
    "Total Cases":"5,226",
    "New Cases":"+44",
    "Total Deaths":"37",
    "New Deaths":0,
    "Total Recovered":"2,039",
    "Active Cases":"3,150",
    "Tot Cases\/ 1M pop":"7,144",
    "Deaths\/ 1M pop":"51",
    "Total Tests":"345,695",
    "Tests\/  1M pop ":"472,555",
    "Population":"731,545",
    "Source":"[1]",
    "Projections":"[projections]"
  },
  "Arizona":{
    "#":"7",
    "Total Cases":"201,661",
    "New Cases":"+374",
    "Total Deaths":"5,030",
    "New Deaths":"+23",
    "Total Recovered":"30,331",
    "Active Cases":"166,300",
    "Tot Cases\/ 1M pop":"27,706",
    "Deaths\/ 1M pop":"691",
    "Total Tests":"1,464,384",
    "Tests\/  1M pop ":"201,187",
    "Population":"7,278,717",
    "Source":"[1]",
    "Projections":"[projections]"
  },
  "Arkansas":{
    "#":"28",
    "Total Cases":"60,856",
    "New Cases":"+478",
    "Total Deaths":"784",
    "New Deaths":"+12",
    "Total Recovered":"54,408",
    "Active Cases":"5,664",
    "Tot Cases\/ 1M pop":"20,166",
    "Deaths\/ 1M pop":"260",
    "Total Tests":"706,970",
    "Tests\/  1M pop ":"234,266",
    "Population":"3,017,804",
    "Source":"[1]\u00a0[2]\u00a0[3]\u00a0[4]",
    "Projections":"[projections]"
  },
  "California":{
    "#":"1",
    "Total Cases":"705,859",
    "New Cases":"+3,810",
    "Total Deaths":"12,938",
    "New Deaths":"+35",
    "Total Recovered":"323,251",
    "Active Cases":"369,670",
    "Tot Cases\/ 1M pop":"17,864",
    "Deaths\/ 1M pop":"327",
    "Total Tests":"11,231,829",
    "Tests\/  1M pop ":"284,262",
    "Population":"39,512,223",
    "Source":"[view by county]\u00a0[1]",
    "Projections":"[projections]"
  },
  "Colorado":{
    "#":"30",
    "Total Cases":"57,223",
    "New Cases":"+182",
    "Total Deaths":"1,944",
    "New Deaths":0,
    "Total Recovered":"24,960",
    "Active Cases":"30,319",
    "Tot Cases\/ 1M pop":"9,937",
    "Deaths\/ 1M pop":"338",
    "Total Tests":"706,067",
    "Tests\/  1M pop ":"122,608",
    "Population":"5,758,736",
    "Source":"[1]",
    "Projections":"[projections]"
  },
  "Connecticut":{
    "#":"32",
    "Total Cases":"52,495",
    "New Cases":0,
    "Total Deaths":"4,465",
    "New Deaths":0,
    "Total Recovered":"37,112",
    "Active Cases":"10,918",
    "Tot Cases\/ 1M pop":"14,724",
    "Deaths\/ 1M pop":"1,252",
    "Total Tests":"1,125,398",
    "Tests\/  1M pop ":"315,654",
    "Population":"3,565,287",
    "Source":"[1]\u00a0[2]",
    "Projections":"[projections]"
  },
  "Delaware":{
    "#":"43",
    "Total Cases":"17,349",
    "New Cases":0,
    "Total Deaths":"604",
    "New Deaths":0,
    "Total Recovered":"9,271",
    "Active Cases":"7,474",
    "Tot Cases\/ 1M pop":"17,816",
    "Deaths\/ 1M pop":"620",
    "Total Tests":"232,884",
    "Tests\/  1M pop ":"239,159",
    "Population":"973,764",
    "Source":"[1]",
    "Projections":"[projections]"
  },
  "District Of Columbia":{
    "#":"44",
    "Total Cases":"13,959",
    "New Cases":"+34",
    "Total Deaths":"606",
    "New Deaths":"+1",
    "Total Recovered":"11,087",
    "Active Cases":"2,266",
    "Tot Cases\/ 1M pop":"19,779",
    "Deaths\/ 1M pop":"859",
    "Total Tests":"288,089",
    "Tests\/  1M pop ":"408,203",
    "Population":"705,749",
    "Source":"[1]",
    "Projections":"[projections]"
  },
  "Florida":{
    "#":"3",
    "Total Cases":"621,586",
    "New Cases":"+2,583",
    "Total Deaths":"11,125",
    "New Deaths":"+15",
    "Total Recovered":"76,268",
    "Active Cases":"534,193",
    "Tot Cases\/ 1M pop":"28,941",
    "Deaths\/ 1M pop":"518",
    "Total Tests":"4,606,568",
    "Tests\/  1M pop ":"214,481",
    "Population":"21,477,737",
    "Source":"[view by county]\u00a0[1]\u00a0[2]\u00a0[3]",
    "Projections":"[projections]"
  },
  "Georgia":{
    "#":"5",
    "Total Cases":"268,973",
    "New Cases":"+1,215",
    "Total Deaths":"5,604",
    "New Deaths":"+28",
    "Total Recovered":"48,583",
    "Active Cases":"214,786",
    "Tot Cases\/ 1M pop":"25,333",
    "Deaths\/ 1M pop":"528",
    "Total Tests":"2,604,448",
    "Tests\/  1M pop ":"245,299",
    "Population":"10,617,423",
    "Source":"[1]",
    "Projections":"[projections]"
  },
  "Hawaii":{
    "#":"50",
    "Total Cases":"8,339",
    "New Cases":"+200",
    "Total Deaths":"63",
    "New Deaths":"+1",
    "Total Recovered":"2,520",
    "Active Cases":"5,756",
    "Tot Cases\/ 1M pop":"5,890",
    "Deaths\/ 1M pop":"44",
    "Total Tests":"260,737",
    "Tests\/  1M pop ":"184,153",
    "Population":"1,415,872",
    "Source":"[1]\u00a0[2]\u00a0[3]",
    "Projections":"[projections]"
  },
  "Idaho":{
    "#":"39",
    "Total Cases":"31,867",
    "New Cases":"+190",
    "Total Deaths":"359",
    "New Deaths":"+1",
    "Total Recovered":"14,712",
    "Active Cases":"16,796",
    "Tot Cases\/ 1M pop":"17,832",
    "Deaths\/ 1M pop":"201",
    "Total Tests":"253,702",
    "Tests\/  1M pop ":"141,966",
    "Population":"1,787,065",
    "Source":"[1]\u00a0[2]\u00a0[3]",
    "Projections":"[projections]"
  },
  "Illinois":{
    "#":"6",
    "Total Cases":"235,057",
    "New Cases":"+1,992",
    "Total Deaths":"8,228",
    "New Deaths":"+11",
    "Total Recovered":"152,361",
    "Active Cases":"74,468",
    "Tot Cases\/ 1M pop":"18,550",
    "Deaths\/ 1M pop":"649",
    "Total Tests":"4,016,782",
    "Tests\/  1M pop ":"316,985",
    "Population":"12,671,821",
    "Source":"[1]\u00a0[2]\u00a0[3]\u00a0[4]",
    "Projections":"[projections]"
  },
  "Indiana":{
    "#":"20",
    "Total Cases":"93,313",
    "New Cases":"+879",
    "Total Deaths":"3,291",
    "New Deaths":"+6",
    "Total Recovered":"70,534",
    "Active Cases":"19,488",
    "Tot Cases\/ 1M pop":"13,861",
    "Deaths\/ 1M pop":"489",
    "Total Tests":"1,411,760",
    "Tests\/  1M pop ":"209,702",
    "Population":"6,732,219",
    "Source":"[1]\u00a0[2]",
    "Projections":"[projections]"
  },
  "Iowa":{
    "#":"27",
    "Total Cases":"64,274",
    "New Cases":"+818",
    "Total Deaths":"1,112",
    "New Deaths":"+3",
    "Total Recovered":"46,565",
    "Active Cases":"16,597",
    "Tot Cases\/ 1M pop":"20,372",
    "Deaths\/ 1M pop":"352",
    "Total Tests":"630,573",
    "Tests\/  1M pop ":"199,860",
    "Population":"3,155,070",
    "Source":"[1]\u00a0[2]",
    "Projections":"[projections]"
  },
  "Kansas":{
    "#":"36",
    "Total Cases":"41,907",
    "New Cases":"+126",
    "Total Deaths":"451",
    "New Deaths":0,
    "Total Recovered":"26,337",
    "Active Cases":"15,119",
    "Tot Cases\/ 1M pop":"14,385",
    "Deaths\/ 1M pop":"155",
    "Total Tests":"403,147",
    "Tests\/  1M pop ":"138,381",
    "Population":"2,913,314",
    "Source":"[1]\u00a0[2]\u00a0[3]\u00a0[4]\u00a0[5]\u00a0[6]\u00a0[7]\u00a0[8]",
    "Projections":"[projections]"
  },
  "Kentucky":{
    "#":"35",
    "Total Cases":"48,032",
    "New Cases":"+455",
    "Total Deaths":"930",
    "New Deaths":"+9",
    "Total Recovered":"10,328",
    "Active Cases":"36,774",
    "Tot Cases\/ 1M pop":"10,751",
    "Deaths\/ 1M pop":"208",
    "Total Tests":"871,811",
    "Tests\/  1M pop ":"195,138",
    "Population":"4,467,673",
    "Source":"[1]\u00a0[2]\u00a0[3]",
    "Projections":"[projections]"
  },
  "Louisiana":{
    "#":"11",
    "Total Cases":"147,867",
    "New Cases":"+1,624",
    "Total Deaths":"4,931",
    "New Deaths":"+27",
    "Total Recovered":"127,918",
    "Active Cases":"15,018",
    "Tot Cases\/ 1M pop":"31,808",
    "Deaths\/ 1M pop":"1,061",
    "Total Tests":"1,868,750",
    "Tests\/  1M pop ":"401,986",
    "Population":"4,648,794",
    "Source":"[view by county]\u00a0[1]",
    "Projections":"[projections]"
  },
  "Maine":{
    "#":"54",
    "Total Cases":"4,512",
    "New Cases":"+23",
    "Total Deaths":"132",
    "New Deaths":0,
    "Total Recovered":"3,910",
    "Active Cases":"470",
    "Tot Cases\/ 1M pop":"3,357",
    "Deaths\/ 1M pop":"98",
    "Total Tests":"268,733",
    "Tests\/  1M pop ":"199,919",
    "Population":"1,344,212",
    "Source":"[1]\u00a0[2]",
    "Projections":"[projections]"
  },
  "Maryland":{
    "#":"19",
    "Total Cases":"107,791",
    "New Cases":"+497",
    "Total Deaths":"3,752",
    "New Deaths":"+6",
    "Total Recovered":"6,124",
    "Active Cases":"97,915",
    "Tot Cases\/ 1M pop":"17,829",
    "Deaths\/ 1M pop":"621",
    "Total Tests":"1,919,515",
    "Tests\/  1M pop ":"317,502",
    "Population":"6,045,680",
    "Source":"[1]",
    "Projections":"[projections]"
  },
  "Massachusetts":{
    "#":"13",
    "Total Cases":"128,229",
    "New Cases":"+199",
    "Total Deaths":"9,049",
    "New Deaths":"+13",
    "Total Recovered":"103,920",
    "Active Cases":"15,260",
    "Tot Cases\/ 1M pop":"18,604",
    "Deaths\/ 1M pop":"1,313",
    "Total Tests":"1,913,243",
    "Tests\/  1M pop ":"277,583",
    "Population":"6,892,503",
    "Source":"[1]",
    "Projections":"[projections]"
  },
  "Michigan":{
    "#":"18",
    "Total Cases":"112,526",
    "New Cases":"+551",
    "Total Deaths":"6,748",
    "New Deaths":"+3",
    "Total Recovered":"76,151",
    "Active Cases":"29,627",
    "Tot Cases\/ 1M pop":"11,267",
    "Deaths\/ 1M pop":"676",
    "Total Tests":"3,033,894",
    "Tests\/  1M pop ":"303,789",
    "Population":"9,986,857",
    "Source":"[1]\u00a0[2]\u00a0[3]\u00a0[4]",
    "Projections":"[projections]"
  },
  "Minnesota":{
    "#":"25",
    "Total Cases":"75,189",
    "New Cases":"+932",
    "Total Deaths":"1,865",
    "New Deaths":"+2",
    "Total Recovered":"66,916",
    "Active Cases":"6,408",
    "Tot Cases\/ 1M pop":"13,332",
    "Deaths\/ 1M pop":"331",
    "Total Tests":"1,478,432",
    "Tests\/  1M pop ":"262,150",
    "Population":"5,639,632",
    "Source":"[1]\u00a0[2]",
    "Projections":"[projections]"
  },
  "Mississippi":{
    "#":"22",
    "Total Cases":"82,676",
    "New Cases":"+647",
    "Total Deaths":"2,441",
    "New Deaths":"+14",
    "Total Recovered":"62,707",
    "Active Cases":"17,528",
    "Tot Cases\/ 1M pop":"27,780",
    "Deaths\/ 1M pop":"820",
    "Total Tests":"621,047",
    "Tests\/  1M pop ":"208,675",
    "Population":"2,976,149",
    "Source":"[1]\u00a0[2]",
    "Projections":"[projections]"
  },
  "Missouri":{
    "#":"21",
    "Total Cases":"83,655",
    "New Cases":"+1,161",
    "Total Deaths":"1,627",
    "New Deaths":0,
    "Total Recovered":"12,710",
    "Active Cases":"69,318",
    "Tot Cases\/ 1M pop":"13,630",
    "Deaths\/ 1M pop":"265",
    "Total Tests":"1,043,056",
    "Tests\/  1M pop ":"169,950",
    "Population":"6,137,428",
    "Source":"[1]\u00a0[2]\u00a0[3]\u00a0[4]\u00a0[5]\u00a0[6]\u00a0[7]",
    "Projections":"[projections]"
  },
  "Montana":{
    "#":"51",
    "Total Cases":"7,340",
    "New Cases":"+89",
    "Total Deaths":"104",
    "New Deaths":0,
    "Total Recovered":"5,283",
    "Active Cases":"1,953",
    "Tot Cases\/ 1M pop":"6,868",
    "Deaths\/ 1M pop":"97",
    "Total Tests":"246,661",
    "Tests\/  1M pop ":"230,788",
    "Population":"1,068,778",
    "Source":"[1]\u00a0[2]\u00a0[3]\u00a0[4]",
    "Projections":"[projections]"
  },
  "Nebraska":{
    "#":"37",
    "Total Cases":"34,046",
    "New Cases":"+293",
    "Total Deaths":"392",
    "New Deaths":0,
    "Total Recovered":"25,969",
    "Active Cases":"7,685",
    "Tot Cases\/ 1M pop":"17,600",
    "Deaths\/ 1M pop":"203",
    "Total Tests":"361,878",
    "Tests\/  1M pop ":"187,074",
    "Population":"1,934,408",
    "Source":"[1]\u00a0[2]",
    "Projections":"[projections]"
  },
  "Nevada":{
    "#":"26",
    "Total Cases":"68,908",
    "New Cases":"+447",
    "Total Deaths":"1,302",
    "New Deaths":0,
    "Total Recovered":"26,011",
    "Active Cases":"41,595",
    "Tot Cases\/ 1M pop":"22,372",
    "Deaths\/ 1M pop":"423",
    "Total Tests":"850,535",
    "Tests\/  1M pop ":"276,134",
    "Population":"3,080,156",
    "Source":"[1]\u00a0[2]",
    "Projections":"[projections]"
  },
  "New Hampshire":{
    "#":"52",
    "Total Cases":"7,254",
    "New Cases":"+8",
    "Total Deaths":"432",
    "New Deaths":0,
    "Total Recovered":"6,600",
    "Active Cases":"222",
    "Tot Cases\/ 1M pop":"5,335",
    "Deaths\/ 1M pop":"318",
    "Total Tests":"238,997",
    "Tests\/  1M pop ":"175,770",
    "Population":"1,359,711",
    "Source":"[1]",
    "Projections":"[projections]"
  },
  "New Jersey":{
    "#":"8",
    "Total Cases":"197,094",
    "New Cases":"+153",
    "Total Deaths":"16,041",
    "New Deaths":"+3",
    "Total Recovered":"161,592",
    "Active Cases":"19,461",
    "Tot Cases\/ 1M pop":"22,190",
    "Deaths\/ 1M pop":"1,806",
    "Total Tests":"2,836,334",
    "Tests\/  1M pop ":"319,328",
    "Population":"8,882,190",
    "Source":"[view by county]\u00a0[1]",
    "Projections":"[projections]"
  },
  "New Mexico":{
    "#":"41",
    "Total Cases":"25,283",
    "New Cases":"+105",
    "Total Deaths":"770",
    "New Deaths":"+1",
    "Total Recovered":"12,913",
    "Active Cases":"11,600",
    "Tot Cases\/ 1M pop":"12,058",
    "Deaths\/ 1M pop":"367",
    "Total Tests":"756,933",
    "Tests\/  1M pop ":"360,989",
    "Population":"2,096,829",
    "Source":"[1]\u00a0[2]",
    "Projections":"[projections]"
  },
  "New York":{
    "#":"4",
    "Total Cases":"465,375",
    "New Cases":"+780",
    "Total Deaths":"33,021",
    "New Deaths":"+9",
    "Total Recovered":"370,318",
    "Active Cases":"62,036",
    "Tot Cases\/ 1M pop":"23,922",
    "Deaths\/ 1M pop":"1,697",
    "Total Tests":"8,196,792",
    "Tests\/  1M pop ":"421,352",
    "Population":"19,453,561",
    "Source":"[view by county]\u00a0[1]\u00a0[2]\u00a0[3]",
    "Projections":"[projections]"
  },
  "North Carolina":{
    "#":"9",
    "Total Cases":"166,615",
    "New Cases":"+992",
    "Total Deaths":"2,716",
    "New Deaths":"+9",
    "Total Recovered":"136,630",
    "Active Cases":"27,269",
    "Tot Cases\/ 1M pop":"15,886",
    "Deaths\/ 1M pop":"259",
    "Total Tests":"2,243,273",
    "Tests\/  1M pop ":"213,888",
    "Population":"10,488,084",
    "Source":"[1]\u00a0[2]\u00a0[3]",
    "Projections":"[projections]"
  },
  "North Dakota":{
    "#":"47",
    "Total Cases":"11,702",
    "New Cases":"+218",
    "Total Deaths":"142",
    "New Deaths":"+1",
    "Total Recovered":"9,079",
    "Active Cases":"2,481",
    "Tot Cases\/ 1M pop":"15,356",
    "Deaths\/ 1M pop":"186",
    "Total Tests":"201,203",
    "Tests\/  1M pop ":"264,024",
    "Population":"762,062",
    "Source":"[1]\u00a0[2]",
    "Projections":"[projections]"
  },
  "Ohio":{
    "#":"15",
    "Total Cases":"122,394",
    "New Cases":"+1,013",
    "Total Deaths":"4,138",
    "New Deaths":"+6",
    "Total Recovered":"101,185",
    "Active Cases":"17,071",
    "Tot Cases\/ 1M pop":"10,471",
    "Deaths\/ 1M pop":"354",
    "Total Tests":"2,190,404",
    "Tests\/  1M pop ":"187,389",
    "Population":"11,689,100",
    "Source":"[view by county]\u00a0[1]\u00a0[2]\u00a0[3]",
    "Projections":"[projections]"
  },
  "Oklahoma":{
    "#":"29",
    "Total Cases":"58,020",
    "New Cases":"+667",
    "Total Deaths":"799",
    "New Deaths":"+2",
    "Total Recovered":"48,933",
    "Active Cases":"8,288",
    "Tot Cases\/ 1M pop":"14,663",
    "Deaths\/ 1M pop":"202",
    "Total Tests":"874,676",
    "Tests\/  1M pop ":"221,047",
    "Population":"3,956,971",
    "Source":"[1]\u00a0[2]",
    "Projections":"[projections]"
  },
  "Oregon":{
    "#":"40",
    "Total Cases":"26,554",
    "New Cases":"+261",
    "Total Deaths":"458",
    "New Deaths":"+4",
    "Total Recovered":"4,884",
    "Active Cases":"21,212",
    "Tot Cases\/ 1M pop":"6,296",
    "Deaths\/ 1M pop":"109",
    "Total Tests":"553,345",
    "Tests\/  1M pop ":"131,195",
    "Population":"4,217,737",
    "Source":"[1]\u00a0[2]\u00a0[3]",
    "Projections":"[projections]"
  },
  "Pennsylvania":{
    "#":"12",
    "Total Cases":"138,137",
    "New Cases":"+561",
    "Total Deaths":"7,757",
    "New Deaths":0,
    "Total Recovered":"108,923",
    "Active Cases":"21,457",
    "Tot Cases\/ 1M pop":"10,790",
    "Deaths\/ 1M pop":"606",
    "Total Tests":"1,653,874",
    "Tests\/  1M pop ":"129,189",
    "Population":"12,801,989",
    "Source":"[view by county]\u00a0[1]",
    "Projections":"[projections]"
  },
  "Rhode Island":{
    "#":"42",
    "Total Cases":"21,683",
    "New Cases":0,
    "Total Deaths":"1,046",
    "New Deaths":0,
    "Total Recovered":"2,084",
    "Active Cases":"18,553",
    "Tot Cases\/ 1M pop":"20,468",
    "Deaths\/ 1M pop":"987",
    "Total Tests":"504,904",
    "Tests\/  1M pop ":"476,612",
    "Population":"1,059,361",
    "Source":"[1]",
    "Projections":"[projections]"
  },
  "South Carolina":{
    "#":"17",
    "Total Cases":"118,324",
    "New Cases":"+1,075",
    "Total Deaths":"2,709",
    "New Deaths":"+11",
    "Total Recovered":"51,431",
    "Active Cases":"64,184",
    "Tot Cases\/ 1M pop":"22,981",
    "Deaths\/ 1M pop":"526",
    "Total Tests":"999,070",
    "Tests\/  1M pop ":"194,043",
    "Population":"5,148,714",
    "Source":"[1]\u00a0[2]",
    "Projections":"[projections]"
  },
  "South Dakota":{
    "#":"46",
    "Total Cases":"13,322",
    "New Cases":"+380",
    "Total Deaths":"167",
    "New Deaths":0,
    "Total Recovered":"10,511",
    "Active Cases":"2,644",
    "Tot Cases\/ 1M pop":"15,059",
    "Deaths\/ 1M pop":"189",
    "Total Tests":"145,651",
    "Tests\/  1M pop ":"164,641",
    "Population":"884,659",
    "Source":"[1]",
    "Projections":"[projections]"
  },
  "Tennessee":{
    "#":"10",
    "Total Cases":"153,115",
    "New Cases":"+835",
    "Total Deaths":"1,747",
    "New Deaths":"+22",
    "Total Recovered":"114,769",
    "Active Cases":"36,599",
    "Tot Cases\/ 1M pop":"22,421",
    "Deaths\/ 1M pop":"256",
    "Total Tests":"2,185,364",
    "Tests\/  1M pop ":"320,004",
    "Population":"6,829,174",
    "Source":"[1]\u00a0[2]\u00a0[3]",
    "Projections":"[projections]"
  },
  "Texas":{
    "#":"2",
    "Total Cases":"638,947",
    "New Cases":"+2,757",
    "Total Deaths":"12,855",
    "New Deaths":"+67",
    "Total Recovered":"516,083",
    "Active Cases":"110,009",
    "Tot Cases\/ 1M pop":"22,036",
    "Deaths\/ 1M pop":"443",
    "Total Tests":"5,345,631",
    "Tests\/  1M pop ":"184,358",
    "Population":"28,995,881",
    "Source":"[view by county]\u00a0[1]\u00a0[2]",
    "Projections":"[projections]"
  },
  "Utah":{
    "#":"33",
    "Total Cases":"51,854",
    "New Cases":"+448",
    "Total Deaths":"407",
    "New Deaths":0,
    "Total Recovered":"43,724",
    "Active Cases":"7,723",
    "Tot Cases\/ 1M pop":"16,174",
    "Deaths\/ 1M pop":"127",
    "Total Tests":"810,646",
    "Tests\/  1M pop ":"252,856",
    "Population":"3,205,958",
    "Source":"[1]",
    "Projections":"[projections]"
  },
  "Vermont":{
    "#":"56",
    "Total Cases":"1,616",
    "New Cases":"+11",
    "Total Deaths":"58",
    "New Deaths":0,
    "Total Recovered":"1,421",
    "Active Cases":"137",
    "Tot Cases\/ 1M pop":"2,590",
    "Deaths\/ 1M pop":"93",
    "Total Tests":"133,275",
    "Tests\/  1M pop ":"213,585",
    "Population":"623,989",
    "Source":"[1]",
    "Projections":"[projections]"
  },
  "Virginia":{
    "#":"16",
    "Total Cases":"119,747",
    "New Cases":"+938",
    "Total Deaths":"2,569",
    "New Deaths":"+1",
    "Total Recovered":"14,957",
    "Active Cases":"102,221",
    "Tot Cases\/ 1M pop":"14,029",
    "Deaths\/ 1M pop":"301",
    "Total Tests":"1,678,614",
    "Tests\/  1M pop ":"196,662",
    "Population":"8,535,519",
    "Source":"[1]\u00a0[2]",
    "Projections":"[projections]"
  },
  "Washington":{
    "#":"23",
    "Total Cases":"76,080",
    "New Cases":"+270",
    "Total Deaths":"1,905",
    "New Deaths":0,
    "Total Recovered":"28,498",
    "Active Cases":"45,677",
    "Tot Cases\/ 1M pop":"9,991",
    "Deaths\/ 1M pop":"250",
    "Total Tests":"1,461,354",
    "Tests\/  1M pop ":"191,907",
    "Population":"7,614,893",
    "Source":"[view by county]\u00a0[1]",
    "Projections":"[projections]"
  },
  "West Virginia":{
    "#":"48",
    "Total Cases":"10,110",
    "New Cases":"+143",
    "Total Deaths":"213",
    "New Deaths":"+1",
    "Total Recovered":"7,935",
    "Active Cases":"1,962",
    "Tot Cases\/ 1M pop":"5,641",
    "Deaths\/ 1M pop":"119",
    "Total Tests":"426,074",
    "Tests\/  1M pop ":"237,745",
    "Population":"1,792,147",
    "Source":"[1]",
    "Projections":"[projections]"
  },
  "Wisconsin":{
    "#":"24",
    "Total Cases":"75,337",
    "New Cases":"+537",
    "Total Deaths":"1,122",
    "New Deaths":"+3",
    "Total Recovered":"66,699",
    "Active Cases":"7,516",
    "Tot Cases\/ 1M pop":"12,939",
    "Deaths\/ 1M pop":"193",
    "Total Tests":"1,244,639",
    "Tests\/  1M pop ":"213,766",
    "Population":"5,822,434",
    "Source":"[1]\u00a0[2]\u00a0[3]\u00a0[4]\u00a0[5]\u00a0[6]",
    "Projections":"[projections]"
  },
  "Wyoming":{
    "#":"55",
    "Total Cases":"3,820",
    "New Cases":"+36",
    "Total Deaths":"37",
    "New Deaths":0,
    "Total Recovered":"3,116",
    "Active Cases":"667",
    "Tot Cases\/ 1M pop":"6,600",
    "Deaths\/ 1M pop":"64",
    "Total Tests":"113,734",
    "Tests\/  1M pop ":"196,514",
    "Population":"578,759",
    "Source":"[1]\u00a0[2]",
    "Projections":"[projections]"
  }
}