{
  "Alabama":{
    "#":"14",
    "Total Cases":"159,713",
    "New Cases":"+544",
    "Total Deaths":"2,559",
    "New Deaths":"+1",
    "Total Recovered":"67,948",
    "Active Cases":"89,206",
    "Tot Cases\/ 1M pop":"32,573",
    "Deaths\/ 1M pop":"522",
    "Total Tests":"1,226,796",
    "Tests\/  1M pop ":"250,204",
    "Population":"4,903,185",
    "Source":"[1]",
    "Projections":"[projections]"
  },
  "Alaska":{
    "#":"48",
    "Total Cases":"8,613",
    "New Cases":"+208",
    "Total Deaths":"58",
    "New Deaths":0,
    "Total Recovered":"4,856",
    "Active Cases":"3,699",
    "Tot Cases\/ 1M pop":"11,774",
    "Deaths\/ 1M pop":"79",
    "Total Tests":"476,818",
    "Tests\/  1M pop ":"651,796",
    "Population":"731,545",
    "Source":"[1]",
    "Projections":"[projections]"
  },
  "Arizona":{
    "#":"7",
    "Total Cases":"221,070",
    "New Cases":"+316",
    "Total Deaths":"5,707",
    "New Deaths":"+1",
    "Total Recovered":"35,838",
    "Active Cases":"179,525",
    "Tot Cases\/ 1M pop":"30,372",
    "Deaths\/ 1M pop":"784",
    "Total Tests":"1,800,202",
    "Tests\/  1M pop ":"247,324",
    "Population":"7,278,717",
    "Source":"[1]",
    "Projections":"[projections]"
  },
  "Arkansas":{
    "#":"28",
    "Total Cases":"87,013",
    "New Cases":0,
    "Total Deaths":"1,425",
    "New Deaths":0,
    "Total Recovered":"78,358",
    "Active Cases":"7,230",
    "Tot Cases\/ 1M pop":"28,833",
    "Deaths\/ 1M pop":"472",
    "Total Tests":"1,094,203",
    "Tests\/  1M pop ":"362,583",
    "Population":"3,017,804",
    "Source":"[1]\u00a0[2]\u00a0[3]\u00a0[4]",
    "Projections":"[projections]"
  },
  "California":{
    "#":"1",
    "Total Cases":"834,374",
    "New Cases":"+1,526",
    "Total Deaths":"16,154",
    "New Deaths":"+7",
    "Total Recovered":"427,697",
    "Active Cases":"390,523",
    "Tot Cases\/ 1M pop":"21,117",
    "Deaths\/ 1M pop":"409",
    "Total Tests":"15,301,681",
    "Tests\/  1M pop ":"387,264",
    "Population":"39,512,223",
    "Source":"[view by county]\u00a0[1]",
    "Projections":"[projections]"
  },
  "Colorado":{
    "#":"31",
    "Total Cases":"73,076",
    "New Cases":0,
    "Total Deaths":"2,068",
    "New Deaths":0,
    "Total Recovered":"32,494",
    "Active Cases":"38,514",
    "Tot Cases\/ 1M pop":"12,690",
    "Deaths\/ 1M pop":"359",
    "Total Tests":"950,759",
    "Tests\/  1M pop ":"165,099",
    "Population":"5,758,736",
    "Source":"[1]",
    "Projections":"[projections]"
  },
  "Connecticut":{
    "#":"34",
    "Total Cases":"58,297",
    "New Cases":0,
    "Total Deaths":"4,513",
    "New Deaths":0,
    "Total Recovered":"42,374",
    "Active Cases":"11,410",
    "Tot Cases\/ 1M pop":"16,351",
    "Deaths\/ 1M pop":"1,266",
    "Total Tests":"1,673,975",
    "Tests\/  1M pop ":"469,520",
    "Population":"3,565,287",
    "Source":"[1]\u00a0[2]",
    "Projections":"[projections]"
  },
  "Delaware":{
    "#":"42",
    "Total Cases":"21,363",
    "New Cases":"+120",
    "Total Deaths":"645",
    "New Deaths":0,
    "Total Recovered":"10,880",
    "Active Cases":"9,838",
    "Tot Cases\/ 1M pop":"21,939",
    "Deaths\/ 1M pop":"662",
    "Total Tests":"294,759",
    "Tests\/  1M pop ":"302,701",
    "Population":"973,764",
    "Source":"[1]",
    "Projections":"[projections]"
  },
  "District Of Columbia":{
    "#":"44",
    "Total Cases":"15,547",
    "New Cases":"+28",
    "Total Deaths":"631",
    "New Deaths":0,
    "Total Recovered":"12,306",
    "Active Cases":"2,610",
    "Tot Cases\/ 1M pop":"22,029",
    "Deaths\/ 1M pop":"894",
    "Total Tests":"401,568",
    "Tests\/  1M pop ":"568,995",
    "Population":"705,749",
    "Source":"[1]",
    "Projections":"[projections]"
  },
  "Florida":{
    "#":"3",
    "Total Cases":"717,874",
    "New Cases":"+1,415",
    "Total Deaths":"14,722",
    "New Deaths":"+44",
    "Total Recovered":"373,146",
    "Active Cases":"330,006",
    "Tot Cases\/ 1M pop":"33,424",
    "Deaths\/ 1M pop":"685",
    "Total Tests":"5,419,897",
    "Tests\/  1M pop ":"252,350",
    "Population":"21,477,737",
    "Source":"[view by county]\u00a0[1]\u00a0[2]\u00a0[3]",
    "Projections":"[projections]"
  },
  "Georgia":{
    "#":"5",
    "Total Cases":"323,714",
    "New Cases":"+789",
    "Total Deaths":"7,192",
    "New Deaths":"+30",
    "Total Recovered":"113,086",
    "Active Cases":"203,436",
    "Tot Cases\/ 1M pop":"30,489",
    "Deaths\/ 1M pop":"677",
    "Total Tests":"3,339,684",
    "Tests\/  1M pop ":"314,548",
    "Population":"10,617,423",
    "Source":"[1]",
    "Projections":"[projections]"
  },
  "Hawaii":{
    "#":"46",
    "Total Cases":"12,804",
    "New Cases":0,
    "Total Deaths":"159",
    "New Deaths":0,
    "Total Recovered":"10,446",
    "Active Cases":"2,199",
    "Tot Cases\/ 1M pop":"9,043",
    "Deaths\/ 1M pop":"112",
    "Total Tests":"436,462",
    "Tests\/  1M pop ":"308,264",
    "Population":"1,415,872",
    "Source":"[1]\u00a0[2]\u00a0[3]\u00a0[4]",
    "Projections":"[projections]"
  },
  "Idaho":{
    "#":"36",
    "Total Cases":"43,964",
    "New Cases":0,
    "Total Deaths":"482",
    "New Deaths":0,
    "Total Recovered":"22,930",
    "Active Cases":"20,552",
    "Tot Cases\/ 1M pop":"24,601",
    "Deaths\/ 1M pop":"270",
    "Total Tests":"318,167",
    "Tests\/  1M pop ":"178,039",
    "Population":"1,787,065",
    "Source":"[1]\u00a0[2]\u00a0[3]",
    "Projections":"[projections]"
  },
  "Illinois":{
    "#":"6",
    "Total Cases":"306,133",
    "New Cases":"+1,853",
    "Total Deaths":"9,054",
    "New Deaths":"+14",
    "Total Recovered":"210,984",
    "Active Cases":"86,095",
    "Tot Cases\/ 1M pop":"24,159",
    "Deaths\/ 1M pop":"714",
    "Total Tests":"5,924,956",
    "Tests\/  1M pop ":"467,569",
    "Population":"12,671,821",
    "Source":"[1]\u00a0[2]\u00a0[3]\u00a0[4]",
    "Projections":"[projections]"
  },
  "Indiana":{
    "#":"22",
    "Total Cases":"125,976",
    "New Cases":"+830",
    "Total Deaths":"3,681",
    "New Deaths":"+7",
    "Total Recovered":"96,845",
    "Active Cases":"25,450",
    "Tot Cases\/ 1M pop":"18,712",
    "Deaths\/ 1M pop":"547",
    "Total Tests":"2,181,850",
    "Tests\/  1M pop ":"324,091",
    "Population":"6,732,219",
    "Source":"[1]\u00a0[2]",
    "Projections":"[projections]"
  },
  "Iowa":{
    "#":"25",
    "Total Cases":"92,985",
    "New Cases":"+392",
    "Total Deaths":"1,389",
    "New Deaths":"+6",
    "Total Recovered":"71,884",
    "Active Cases":"19,712",
    "Tot Cases\/ 1M pop":"29,472",
    "Deaths\/ 1M pop":"440",
    "Total Tests":"824,528",
    "Tests\/  1M pop ":"261,334",
    "Population":"3,155,070",
    "Source":"[1]\u00a0[2]",
    "Projections":"[projections]"
  },
  "Kansas":{
    "#":"33",
    "Total Cases":"62,708",
    "New Cases":"+398",
    "Total Deaths":"706",
    "New Deaths":"+8",
    "Total Recovered":"47,503",
    "Active Cases":"14,499",
    "Tot Cases\/ 1M pop":"21,525",
    "Deaths\/ 1M pop":"242",
    "Total Tests":"541,106",
    "Tests\/  1M pop ":"185,736",
    "Population":"2,913,314",
    "Source":"[1]\u00a0[2]\u00a0[3]\u00a0[4]\u00a0[5]\u00a0[6]\u00a0[7]\u00a0[8]\u00a0[9]",
    "Projections":"[projections]"
  },
  "Kentucky":{
    "#":"32",
    "Total Cases":"72,617",
    "New Cases":0,
    "Total Deaths":"1,209",
    "New Deaths":0,
    "Total Recovered":"12,121",
    "Active Cases":"59,287",
    "Tot Cases\/ 1M pop":"16,254",
    "Deaths\/ 1M pop":"271",
    "Total Tests":"1,520,236",
    "Tests\/  1M pop ":"340,275",
    "Population":"4,467,673",
    "Source":"[1]\u00a0[2]\u00a0[3]",
    "Projections":"[projections]"
  },
  "Louisiana":{
    "#":"12",
    "Total Cases":"168,512",
    "New Cases":"+218",
    "Total Deaths":"5,586",
    "New Deaths":"+9",
    "Total Recovered":"154,163",
    "Active Cases":"8,763",
    "Tot Cases\/ 1M pop":"36,249",
    "Deaths\/ 1M pop":"1,202",
    "Total Tests":"2,389,595",
    "Tests\/  1M pop ":"514,025",
    "Population":"4,648,794",
    "Source":"[view by county]\u00a0[1]",
    "Projections":"[projections]"
  },
  "Maine":{
    "#":"50",
    "Total Cases":"5,545",
    "New Cases":"+26",
    "Total Deaths":"142",
    "New Deaths":0,
    "Total Recovered":"4,807",
    "Active Cases":"596",
    "Tot Cases\/ 1M pop":"4,125",
    "Deaths\/ 1M pop":"106",
    "Total Tests":"459,167",
    "Tests\/  1M pop ":"341,588",
    "Population":"1,344,212",
    "Source":"[1]\u00a0[2]",
    "Projections":"[projections]"
  },
  "Maryland":{
    "#":"21",
    "Total Cases":"127,791",
    "New Cases":"+501",
    "Total Deaths":"3,961",
    "New Deaths":"+3",
    "Total Recovered":"7,657",
    "Active Cases":"116,173",
    "Tot Cases\/ 1M pop":"21,138",
    "Deaths\/ 1M pop":"655",
    "Total Tests":"2,734,800",
    "Tests\/  1M pop ":"452,356",
    "Population":"6,045,680",
    "Source":"[1]",
    "Projections":"[projections]"
  },
  "Massachusetts":{
    "#":"19",
    "Total Cases":"134,947",
    "New Cases":0,
    "Total Deaths":"9,510",
    "New Deaths":0,
    "Total Recovered":"113,768",
    "Active Cases":"11,669",
    "Tot Cases\/ 1M pop":"19,579",
    "Deaths\/ 1M pop":"1,380",
    "Total Tests":"2,566,294",
    "Tests\/  1M pop ":"372,331",
    "Population":"6,892,503",
    "Source":"[1]",
    "Projections":"[projections]"
  },
  "Michigan":{
    "#":"17",
    "Total Cases":"142,726",
    "New Cases":"+1,455",
    "Total Deaths":"7,139",
    "New Deaths":"+15",
    "Total Recovered":"99,521",
    "Active Cases":"36,066",
    "Tot Cases\/ 1M pop":"14,291",
    "Deaths\/ 1M pop":"715",
    "Total Tests":"4,098,018",
    "Tests\/  1M pop ":"410,341",
    "Population":"9,986,857",
    "Source":"[1]\u00a0[2]\u00a0[3]\u00a0[4]",
    "Projections":"[projections]"
  },
  "Minnesota":{
    "#":"23",
    "Total Cases":"104,799",
    "New Cases":"+973",
    "Total Deaths":"2,136",
    "New Deaths":"+3",
    "Total Recovered":"94,416",
    "Active Cases":"8,247",
    "Tot Cases\/ 1M pop":"18,583",
    "Deaths\/ 1M pop":"379",
    "Total Tests":"2,169,786",
    "Tests\/  1M pop ":"384,739",
    "Population":"5,639,632",
    "Source":"[1]\u00a0[2]",
    "Projections":"[projections]"
  },
  "Mississippi":{
    "#":"24",
    "Total Cases":"100,703",
    "New Cases":"+215",
    "Total Deaths":"3,013",
    "New Deaths":0,
    "Total Recovered":"90,577",
    "Active Cases":"7,113",
    "Tot Cases\/ 1M pop":"33,837",
    "Deaths\/ 1M pop":"1,012",
    "Total Tests":"904,005",
    "Tests\/  1M pop ":"303,750",
    "Population":"2,976,149",
    "Source":"[1]\u00a0[2]\u00a0[3]",
    "Projections":"[projections]"
  },
  "Missouri":{
    "#":"18",
    "Total Cases":"137,489",
    "New Cases":0,
    "Total Deaths":"2,307",
    "New Deaths":0,
    "Total Recovered":"23,211",
    "Active Cases":"111,971",
    "Tot Cases\/ 1M pop":"22,402",
    "Deaths\/ 1M pop":"376",
    "Total Tests":"2,010,240",
    "Tests\/  1M pop ":"327,538",
    "Population":"6,137,428",
    "Source":"[1]\u00a0[2]\u00a0[3]\u00a0[4]\u00a0[5]\u00a0[6]\u00a0[7]\u00a0[8]",
    "Projections":"[projections]"
  },
  "Montana":{
    "#":"45",
    "Total Cases":"14,847",
    "New Cases":"+212",
    "Total Deaths":"190",
    "New Deaths":"+3",
    "Total Recovered":"9,649",
    "Active Cases":"5,008",
    "Tot Cases\/ 1M pop":"13,892",
    "Deaths\/ 1M pop":"178",
    "Total Tests":"369,975",
    "Tests\/  1M pop ":"346,166",
    "Population":"1,068,778",
    "Source":"[1]\u00a0[2]\u00a0[3]\u00a0[4]",
    "Projections":"[projections]"
  },
  "Nebraska":{
    "#":"35",
    "Total Cases":"47,807",
    "New Cases":0,
    "Total Deaths":"501",
    "New Deaths":0,
    "Total Recovered":"34,613",
    "Active Cases":"12,693",
    "Tot Cases\/ 1M pop":"24,714",
    "Deaths\/ 1M pop":"259",
    "Total Tests":"477,266",
    "Tests\/  1M pop ":"246,725",
    "Population":"1,934,408",
    "Source":"[1]\u00a0[2]",
    "Projections":"[projections]"
  },
  "Nevada":{
    "#":"29",
    "Total Cases":"82,437",
    "New Cases":"+337",
    "Total Deaths":"1,623",
    "New Deaths":0,
    "Total Recovered":"60,000",
    "Active Cases":"20,814",
    "Tot Cases\/ 1M pop":"26,764",
    "Deaths\/ 1M pop":"527",
    "Total Tests":"1,089,057",
    "Tests\/  1M pop ":"353,572",
    "Population":"3,080,156",
    "Source":"[1]\u00a0[2]",
    "Projections":"[projections]"
  },
  "New Hampshire":{
    "#":"47",
    "Total Cases":"8,645",
    "New Cases":0,
    "Total Deaths":"443",
    "New Deaths":0,
    "Total Recovered":"7,710",
    "Active Cases":"492",
    "Tot Cases\/ 1M pop":"6,358",
    "Deaths\/ 1M pop":"326",
    "Total Tests":"310,795",
    "Tests\/  1M pop ":"228,574",
    "Population":"1,359,711",
    "Source":"[1]\u00a0[2]",
    "Projections":"[projections]"
  },
  "New Jersey":{
    "#":"9",
    "Total Cases":"212,220",
    "New Cases":"+406",
    "Total Deaths":"16,260",
    "New Deaths":"+2",
    "Total Recovered":"173,185",
    "Active Cases":"22,775",
    "Tot Cases\/ 1M pop":"23,893",
    "Deaths\/ 1M pop":"1,831",
    "Total Tests":"3,758,058",
    "Tests\/  1M pop ":"423,100",
    "Population":"8,882,190",
    "Source":"[view by county]\u00a0[1]",
    "Projections":"[projections]"
  },
  "New Mexico":{
    "#":"38",
    "Total Cases":"30,477",
    "New Cases":0,
    "Total Deaths":"892",
    "New Deaths":0,
    "Total Recovered":"17,270",
    "Active Cases":"12,315",
    "Tot Cases\/ 1M pop":"14,535",
    "Deaths\/ 1M pop":"425",
    "Total Tests":"947,945",
    "Tests\/  1M pop ":"452,085",
    "Population":"2,096,829",
    "Source":"[1]\u00a0[2]",
    "Projections":"[projections]"
  },
  "New York":{
    "#":"4",
    "Total Cases":"500,121",
    "New Cases":"+860",
    "Total Deaths":"33,313",
    "New Deaths":"+13",
    "Total Recovered":"399,639",
    "Active Cases":"67,169",
    "Tot Cases\/ 1M pop":"25,708",
    "Deaths\/ 1M pop":"1,712",
    "Total Tests":"11,297,024",
    "Tests\/  1M pop ":"580,718",
    "Population":"19,453,561",
    "Source":"[view by county]\u00a0[1]\u00a0[2]\u00a0[3]",
    "Projections":"[projections]"
  },
  "North Carolina":{
    "#":"8",
    "Total Cases":"219,754",
    "New Cases":"+2,258",
    "Total Deaths":"3,637",
    "New Deaths":"+3",
    "Total Recovered":"184,422",
    "Active Cases":"31,695",
    "Tot Cases\/ 1M pop":"20,953",
    "Deaths\/ 1M pop":"347",
    "Total Tests":"3,188,371",
    "Tests\/  1M pop ":"303,999",
    "Population":"10,488,084",
    "Source":"[1]\u00a0[2]\u00a0[3]",
    "Projections":"[projections]"
  },
  "North Dakota":{
    "#":"41",
    "Total Cases":"23,862",
    "New Cases":"+312",
    "Total Deaths":"277",
    "New Deaths":"+3",
    "Total Recovered":"19,892",
    "Active Cases":"3,693",
    "Tot Cases\/ 1M pop":"31,312",
    "Deaths\/ 1M pop":"363",
    "Total Tests":"248,652",
    "Tests\/  1M pop ":"326,288",
    "Population":"762,062",
    "Source":"[1]\u00a0[2]",
    "Projections":"[projections]"
  },
  "Ohio":{
    "#":"13",
    "Total Cases":"159,996",
    "New Cases":"+1,037",
    "Total Deaths":"4,936",
    "New Deaths":"+6",
    "Total Recovered":"137,633",
    "Active Cases":"17,427",
    "Tot Cases\/ 1M pop":"13,688",
    "Deaths\/ 1M pop":"422",
    "Total Tests":"3,378,983",
    "Tests\/  1M pop ":"289,071",
    "Population":"11,689,100",
    "Source":"[view by county]\u00a0[1]\u00a0[2]\u00a0[3]",
    "Projections":"[projections]"
  },
  "Oklahoma":{
    "#":"27",
    "Total Cases":"91,982",
    "New Cases":"+665",
    "Total Deaths":"1,055",
    "New Deaths":"+3",
    "Total Recovered":"78,155",
    "Active Cases":"12,772",
    "Tot Cases\/ 1M pop":"23,246",
    "Deaths\/ 1M pop":"267",
    "Total Tests":"1,262,313",
    "Tests\/  1M pop ":"319,010",
    "Population":"3,956,971",
    "Source":"[1]\u00a0[2]",
    "Projections":"[projections]"
  },
  "Oregon":{
    "#":"37",
    "Total Cases":"34,770",
    "New Cases":0,
    "Total Deaths":"572",
    "New Deaths":0,
    "Total Recovered":"5,752",
    "Active Cases":"28,446",
    "Tot Cases\/ 1M pop":"8,244",
    "Deaths\/ 1M pop":"136",
    "Total Tests":"705,436",
    "Tests\/  1M pop ":"167,255",
    "Population":"4,217,737",
    "Source":"[1]\u00a0[2]\u00a0[3]",
    "Projections":"[projections]"
  },
  "Pennsylvania":{
    "#":"11",
    "Total Cases":"168,550",
    "New Cases":"+387",
    "Total Deaths":"8,304",
    "New Deaths":"+9",
    "Total Recovered":"134,098",
    "Active Cases":"26,148",
    "Tot Cases\/ 1M pop":"13,166",
    "Deaths\/ 1M pop":"649",
    "Total Tests":"2,099,615",
    "Tests\/  1M pop ":"164,007",
    "Population":"12,801,989",
    "Source":"[view by county]\u00a0[1]",
    "Projections":"[projections]"
  },
  "Rhode Island":{
    "#":"39",
    "Total Cases":"25,419",
    "New Cases":"+343",
    "Total Deaths":"1,121",
    "New Deaths":"+3",
    "Total Recovered":"2,346",
    "Active Cases":"21,952",
    "Tot Cases\/ 1M pop":"23,995",
    "Deaths\/ 1M pop":"1,058",
    "Total Tests":"820,305",
    "Tests\/  1M pop ":"774,339",
    "Population":"1,059,361",
    "Source":"[1]\u00a0[2]",
    "Projections":"[projections]"
  },
  "South Carolina":{
    "#":"16",
    "Total Cases":"152,159",
    "New Cases":"+577",
    "Total Deaths":"3,456",
    "New Deaths":"+3",
    "Total Recovered":"73,974",
    "Active Cases":"74,729",
    "Tot Cases\/ 1M pop":"29,553",
    "Deaths\/ 1M pop":"671",
    "Total Tests":"1,512,129",
    "Tests\/  1M pop ":"293,691",
    "Population":"5,148,714",
    "Source":"[1]\u00a0[2]\u00a0[3]",
    "Projections":"[projections]"
  },
  "South Dakota":{
    "#":"40",
    "Total Cases":"24,598",
    "New Cases":"+180",
    "Total Deaths":"248",
    "New Deaths":0,
    "Total Recovered":"20,076",
    "Active Cases":"4,274",
    "Tot Cases\/ 1M pop":"27,805",
    "Deaths\/ 1M pop":"280",
    "Total Tests":"200,443",
    "Tests\/  1M pop ":"226,577",
    "Population":"884,659",
    "Source":"[1]",
    "Projections":"[projections]"
  },
  "Tennessee":{
    "#":"10",
    "Total Cases":"203,699",
    "New Cases":"+2,489",
    "Total Deaths":"2,597",
    "New Deaths":"+20",
    "Total Recovered":"184,404",
    "Active Cases":"16,698",
    "Tot Cases\/ 1M pop":"29,828",
    "Deaths\/ 1M pop":"380",
    "Total Tests":"3,006,185",
    "Tests\/  1M pop ":"440,197",
    "Population":"6,829,174",
    "Source":"[1]\u00a0[2]\u00a0[3]",
    "Projections":"[projections]"
  },
  "Texas":{
    "#":"2",
    "Total Cases":"805,485",
    "New Cases":0,
    "Total Deaths":"16,505",
    "New Deaths":0,
    "Total Recovered":"698,587",
    "Active Cases":"90,393",
    "Tot Cases\/ 1M pop":"27,779",
    "Deaths\/ 1M pop":"569",
    "Total Tests":"7,090,891",
    "Tests\/  1M pop ":"244,548",
    "Population":"28,995,881",
    "Source":"[view by county]\u00a0[1]\u00a0[2]",
    "Projections":"[projections]"
  },
  "Utah":{
    "#":"30",
    "Total Cases":"78,723",
    "New Cases":"+1,105",
    "Total Deaths":"482",
    "New Deaths":"+4",
    "Total Recovered":"57,965",
    "Active Cases":"20,276",
    "Tot Cases\/ 1M pop":"24,555",
    "Deaths\/ 1M pop":"150",
    "Total Tests":"1,131,691",
    "Tests\/  1M pop ":"352,996",
    "Population":"3,205,958",
    "Source":"[1]",
    "Projections":"[projections]"
  },
  "Vermont":{
    "#":"51",
    "Total Cases":"1,817",
    "New Cases":"+32",
    "Total Deaths":"58",
    "New Deaths":0,
    "Total Recovered":"1,625",
    "Active Cases":"134",
    "Tot Cases\/ 1M pop":"2,912",
    "Deaths\/ 1M pop":"93",
    "Total Tests":"167,506",
    "Tests\/  1M pop ":"268,444",
    "Population":"623,989",
    "Source":"[1]",
    "Projections":"[projections]"
  },
  "Virginia":{
    "#":"15",
    "Total Cases":"152,557",
    "New Cases":"+687",
    "Total Deaths":"3,276",
    "New Deaths":"+3",
    "Total Recovered":"17,848",
    "Active Cases":"131,433",
    "Tot Cases\/ 1M pop":"17,873",
    "Deaths\/ 1M pop":"384",
    "Total Tests":"2,294,394",
    "Tests\/  1M pop ":"268,805",
    "Population":"8,535,519",
    "Source":"[1]\u00a0[2]",
    "Projections":"[projections]"
  },
  "Washington":{
    "#":"26",
    "Total Cases":"92,315",
    "New Cases":0,
    "Total Deaths":"2,144",
    "New Deaths":0,
    "Total Recovered":"43,444",
    "Active Cases":"46,727",
    "Tot Cases\/ 1M pop":"12,123",
    "Deaths\/ 1M pop":"282",
    "Total Tests":"1,935,899",
    "Tests\/  1M pop ":"254,225",
    "Population":"7,614,893",
    "Source":"[view by county]\u00a0[1]",
    "Projections":"[projections]"
  },
  "West Virginia":{
    "#":"43",
    "Total Cases":"16,742",
    "New Cases":"+114",
    "Total Deaths":"361",
    "New Deaths":"+3",
    "Total Recovered":"12,051",
    "Active Cases":"4,330",
    "Tot Cases\/ 1M pop":"9,342",
    "Deaths\/ 1M pop":"201",
    "Total Tests":"596,040",
    "Tests\/  1M pop ":"332,584",
    "Population":"1,792,147",
    "Source":"[1]",
    "Projections":"[projections]"
  },
  "Wisconsin":{
    "#":"20",
    "Total Cases":"134,359",
    "New Cases":"+1,696",
    "Total Deaths":"1,381",
    "New Deaths":"+4",
    "Total Recovered":"108,371",
    "Active Cases":"24,607",
    "Tot Cases\/ 1M pop":"23,076",
    "Deaths\/ 1M pop":"237",
    "Total Tests":"1,606,936",
    "Tests\/  1M pop ":"275,990",
    "Population":"5,822,434",
    "Source":"[1]\u00a0[2]\u00a0[3]\u00a0[4]\u00a0[5]\u00a0[6]",
    "Projections":"[projections]"
  },
  "Wyoming":{
    "#":"49",
    "Total Cases":"6,504",
    "New Cases":0,
    "Total Deaths":"53",
    "New Deaths":0,
    "Total Recovered":"5,160",
    "Active Cases":"1,291",
    "Tot Cases\/ 1M pop":"11,238",
    "Deaths\/ 1M pop":"92",
    "Total Tests":"165,242",
    "Tests\/  1M pop ":"285,511",
    "Population":"578,759",
    "Source":"[1]\u00a0[2]",
    "Projections":"[projections]"
  }
}