{
  "Hawaii":{
    "Total Cases":"1,243",
    "New Cases":0,
    "Total Deaths":"22",
    "New Deaths":0,
    "Active Cases":"310",
    "Tot Cases\/ 1M pop":"878",
    "Deaths\/ 1M pop":"16",
    "Total Tests":"114,109",
    "Tests\/  1M pop ":"80,593",
    "Source":"[1]\u00a0[2]\u00a0[3]",
    "Projections":"[projections]"
  },
  "Vermont":{
    "Total Cases":"1,301",
    "New Cases":0,
    "Total Deaths":"56",
    "New Deaths":0,
    "Active Cases":"149",
    "Tot Cases\/ 1M pop":"2,085",
    "Deaths\/ 1M pop":"90",
    "Total Tests":"76,581",
    "Tests\/  1M pop ":"122,728",
    "Source":"[1]",
    "Projections":"[projections]"
  },
  "Alaska":{
    "Total Cases":"1,539",
    "New Cases":0,
    "Total Deaths":"17",
    "New Deaths":0,
    "Active Cases":"902",
    "Tot Cases\/ 1M pop":"2,104",
    "Deaths\/ 1M pop":"23",
    "Total Tests":"146,590",
    "Tests\/  1M pop ":"200,384",
    "Source":"[1]",
    "Projections":"[projections]"
  },
  "Montana":{
    "Total Cases":"1,843",
    "New Cases":0,
    "Total Deaths":"32",
    "New Deaths":0,
    "Active Cases":"936",
    "Tot Cases\/ 1M pop":"1,724",
    "Deaths\/ 1M pop":"30",
    "Total Tests":"118,695",
    "Tests\/  1M pop ":"111,057",
    "Source":"[1]\u00a0[2]\u00a0[3]\u00a0[4]",
    "Projections":"[projections]"
  },
  "Wyoming":{
    "Total Cases":"1,904",
    "New Cases":0,
    "Total Deaths":"21",
    "New Deaths":0,
    "Active Cases":"471",
    "Tot Cases\/ 1M pop":"3,290",
    "Deaths\/ 1M pop":"36",
    "Total Tests":"56,993",
    "Tests\/  1M pop ":"98,474",
    "Source":"[1]\u00a0[2]",
    "Projections":"[projections]"
  },
  "District Of Columbia":{
    "Total Cases":"10,906",
    "New Cases":0,
    "Total Deaths":"568",
    "New Deaths":0,
    "Active Cases":"8,582",
    "Tot Cases\/ 1M pop":"15,453",
    "Deaths\/ 1M pop":"805",
    "Total Tests":"130,220",
    "Tests\/  1M pop ":"184,513",
    "Source":"[1]",
    "Projections":"[projections]"
  },
  "Pennsylvania":{
    "Total Cases":"100,378",
    "New Cases":0,
    "Total Deaths":"6,963",
    "New Deaths":0,
    "Active Cases":"19,694",
    "Tot Cases\/ 1M pop":"7,841",
    "Deaths\/ 1M pop":"544",
    "Total Tests":"931,474",
    "Tests\/  1M pop ":"72,760",
    "Source":"[view by county]\u00a0[1]",
    "Projections":"[projections]"
  },
  "Idaho":{
    "Total Cases":"11,402",
    "New Cases":0,
    "Total Deaths":"102",
    "New Deaths":0,
    "Active Cases":"8,038",
    "Tot Cases\/ 1M pop":"6,380",
    "Deaths\/ 1M pop":"57",
    "Total Tests":"129,540",
    "Tests\/  1M pop ":"72,488",
    "Source":"[1]\u00a0[2]\u00a0[3]",
    "Projections":"[projections]"
  },
  "Massachusetts":{
    "Total Cases":"111,827",
    "New Cases":0,
    "Total Deaths":"8,330",
    "New Deaths":0,
    "Active Cases":"9,150",
    "Tot Cases\/ 1M pop":"16,224",
    "Deaths\/ 1M pop":"1,209",
    "Total Tests":"1,040,987",
    "Tests\/  1M pop ":"151,032",
    "Source":"[1]",
    "Projections":"[projections]"
  },
  "Oregon":{
    "Total Cases":"12,438",
    "New Cases":0,
    "Total Deaths":"237",
    "New Deaths":0,
    "Active Cases":"9,107",
    "Tot Cases\/ 1M pop":"2,949",
    "Deaths\/ 1M pop":"56",
    "Total Tests":"300,069",
    "Tests\/  1M pop ":"71,145",
    "Source":"[1]\u00a0[2]\u00a0[3]",
    "Projections":"[projections]"
  },
  "Delaware":{
    "Total Cases":"12,879",
    "New Cases":0,
    "Total Deaths":"517",
    "New Deaths":0,
    "Active Cases":"5,223",
    "Tot Cases\/ 1M pop":"13,226",
    "Deaths\/ 1M pop":"531",
    "Total Tests":"139,363",
    "Tests\/  1M pop ":"143,118",
    "Source":"[1]",
    "Projections":"[projections]"
  },
  "Georgia":{
    "Total Cases":"120,569",
    "New Cases":0,
    "Total Deaths":"3,026",
    "New Deaths":0,
    "Active Cases":"98,358",
    "Tot Cases\/ 1M pop":"11,356",
    "Deaths\/ 1M pop":"285",
    "Total Tests":"1,293,302",
    "Tests\/  1M pop ":"121,809",
    "Source":"[1]",
    "Projections":"[projections]"
  },
  "Arizona":{
    "Total Cases":"123,824",
    "New Cases":0,
    "Total Deaths":"2,245",
    "New Deaths":0,
    "Active Cases":"106,325",
    "Tot Cases\/ 1M pop":"17,012",
    "Deaths\/ 1M pop":"308",
    "Total Tests":"899,994",
    "Tests\/  1M pop ":"123,647",
    "Source":"[1]",
    "Projections":"[projections]"
  },
  "New Mexico":{
    "Total Cases":"15,291",
    "New Cases":0,
    "Total Deaths":"548",
    "New Deaths":0,
    "Active Cases":"8,380",
    "Tot Cases\/ 1M pop":"7,292",
    "Deaths\/ 1M pop":"261",
    "Total Tests":"424,355",
    "Tests\/  1M pop ":"202,379",
    "Source":"[1]\u00a0[2]",
    "Projections":"[projections]"
  },
  "Illinois":{
    "Total Cases":"155,931",
    "New Cases":0,
    "Total Deaths":"7,394",
    "New Deaths":0,
    "Active Cases":"32,698",
    "Tot Cases\/ 1M pop":"12,305",
    "Deaths\/ 1M pop":"583",
    "Total Tests":"2,012,994",
    "Tests\/  1M pop ":"158,856",
    "Source":"[1]\u00a0[2]\u00a0[3]\u00a0[4]",
    "Projections":"[projections]"
  },
  "Rhode Island":{
    "Total Cases":"17,487",
    "New Cases":0,
    "Total Deaths":"984",
    "New Deaths":0,
    "Active Cases":"14,812",
    "Tot Cases\/ 1M pop":"16,507",
    "Deaths\/ 1M pop":"929",
    "Total Tests":"282,725",
    "Tests\/  1M pop ":"266,883",
    "Source":"[1]",
    "Projections":"[projections]"
  },
  "New Jersey":{
    "Total Cases":"181,366",
    "New Cases":0,
    "Total Deaths":"15,639",
    "New Deaths":0,
    "Active Cases":"84,042",
    "Tot Cases\/ 1M pop":"20,419",
    "Deaths\/ 1M pop":"1,761",
    "Total Tests":"1,700,385",
    "Tests\/  1M pop ":"191,438",
    "Source":"[view by county]\u00a0[1]",
    "Projections":"[projections]"
  },
  "Kentucky":{
    "Total Cases":"19,653",
    "New Cases":0,
    "Total Deaths":"629",
    "New Deaths":0,
    "Active Cases":"13,680",
    "Tot Cases\/ 1M pop":"4,399",
    "Deaths\/ 1M pop":"141",
    "Total Tests":"480,372",
    "Tests\/  1M pop ":"107,522",
    "Source":"[1]\u00a0[2]\u00a0[3]",
    "Projections":"[projections]"
  },
  "Kansas":{
    "Total Cases":"20,241",
    "New Cases":0,
    "Total Deaths":"297",
    "New Deaths":0,
    "Active Cases":"8,640",
    "Tot Cases\/ 1M pop":"6,948",
    "Deaths\/ 1M pop":"102",
    "Total Tests":"231,175",
    "Tests\/  1M pop ":"79,351",
    "Source":"[1]\u00a0[2]\u00a0[3]\u00a0[4]\u00a0[5]\u00a0[6]\u00a0[7]\u00a0[8]",
    "Projections":"[projections]"
  },
  "Oklahoma":{
    "Total Cases":"20,745",
    "New Cases":0,
    "Total Deaths":"424",
    "New Deaths":0,
    "Active Cases":"4,506",
    "Tot Cases\/ 1M pop":"5,243",
    "Deaths\/ 1M pop":"107",
    "Total Tests":"423,285",
    "Tests\/  1M pop ":"106,972",
    "Source":"[1]\u00a0[2]",
    "Projections":"[projections]"
  },
  "Nebraska":{
    "Total Cases":"21,399",
    "New Cases":0,
    "Total Deaths":"288",
    "New Deaths":0,
    "Active Cases":"5,086",
    "Tot Cases\/ 1M pop":"11,062",
    "Deaths\/ 1M pop":"149",
    "Total Tests":"216,481",
    "Tests\/  1M pop ":"111,911",
    "Source":"[1]\u00a0[2]",
    "Projections":"[projections]"
  },
  "Texas":{
    "Total Cases":"274,712",
    "New Cases":0,
    "Total Deaths":"3,340",
    "New Deaths":0,
    "Active Cases":"134,953",
    "Tot Cases\/ 1M pop":"9,474",
    "Deaths\/ 1M pop":"115",
    "Total Tests":"2,820,803",
    "Tests\/  1M pop ":"97,283",
    "Source":"[view by county]\u00a0[1]\u00a0[2]",
    "Projections":"[projections]"
  },
  "Nevada":{
    "Total Cases":"28,515",
    "New Cases":0,
    "Total Deaths":"593",
    "New Deaths":0,
    "Active Cases":"9,014",
    "Tot Cases\/ 1M pop":"9,258",
    "Deaths\/ 1M pop":"193",
    "Total Tests":"443,136",
    "Tests\/  1M pop ":"143,868",
    "Source":"[1]\u00a0[2]",
    "Projections":"[projections]"
  },
  "Arkansas":{
    "Total Cases":"28,939",
    "New Cases":0,
    "Total Deaths":"323",
    "New Deaths":0,
    "Active Cases":"6,510",
    "Tot Cases\/ 1M pop":"9,589",
    "Deaths\/ 1M pop":"107",
    "Total Tests":"389,505",
    "Tests\/  1M pop ":"129,069",
    "Source":"[1]\u00a0[2]",
    "Projections":"[projections]"
  },
  "Florida":{
    "Total Cases":"282,435",
    "New Cases":0,
    "Total Deaths":"4,277",
    "New Deaths":0,
    "Active Cases":"244,868",
    "Tot Cases\/ 1M pop":"13,150",
    "Deaths\/ 1M pop":"199",
    "Total Tests":"2,642,613",
    "Tests\/  1M pop ":"123,040",
    "Source":"[view by county]\u00a0[1]\u00a0[2]\u00a0[3]",
    "Projections":"[projections]"
  },
  "USA Total":{
    "Total Cases":"3,479,483",
    "New Cases":0,
    "Total Deaths":"138,247",
    "New Deaths":0,
    "Active Cases":"1,791,767",
    "Tot Cases\/ 1M pop":"10,512",
    "Deaths\/ 1M pop":"418",
    "Total Tests":"43,252,833",
    "Tests\/  1M pop ":"130,672",
    "Source":0,
    "Projections":0
  },
  "Maine":{
    "Total Cases":"3,558",
    "New Cases":0,
    "Total Deaths":"114",
    "New Deaths":0,
    "Active Cases":"436",
    "Tot Cases\/ 1M pop":"2,647",
    "Deaths\/ 1M pop":"85",
    "Total Tests":"131,698",
    "Tests\/  1M pop ":"97,974",
    "Source":"[1]\u00a0[2]",
    "Projections":"[projections]"
  },
  "Utah":{
    "Total Cases":"30,030",
    "New Cases":0,
    "Total Deaths":"216",
    "New Deaths":0,
    "Active Cases":"12,086",
    "Tot Cases\/ 1M pop":"9,367",
    "Deaths\/ 1M pop":"67",
    "Total Tests":"418,335",
    "Tests\/  1M pop ":"130,487",
    "Source":"[1]",
    "Projections":"[projections]"
  },
  "Missouri":{
    "Total Cases":"30,049",
    "New Cases":0,
    "Total Deaths":"1,133",
    "New Deaths":0,
    "Active Cases":"22,646",
    "Tot Cases\/ 1M pop":"4,896",
    "Deaths\/ 1M pop":"185",
    "Total Tests":"546,272",
    "Tests\/  1M pop ":"89,007",
    "Source":"[1]\u00a0[2]\u00a0[3]\u00a0[4]\u00a0[5]\u00a0[6]\u00a0[7]",
    "Projections":"[projections]"
  },
  "California":{
    "Total Cases":"336,037",
    "New Cases":0,
    "Total Deaths":"7,096",
    "New Deaths":0,
    "Active Cases":"239,829",
    "Tot Cases\/ 1M pop":"8,505",
    "Deaths\/ 1M pop":"180",
    "Total Tests":"5,544,365",
    "Tests\/  1M pop ":"140,320",
    "Source":"[view by county]\u00a0[1]",
    "Projections":"[projections]"
  },
  "Iowa":{
    "Total Cases":"35,607",
    "New Cases":0,
    "Total Deaths":"755",
    "New Deaths":0,
    "Active Cases":"8,126",
    "Tot Cases\/ 1M pop":"11,286",
    "Deaths\/ 1M pop":"239",
    "Total Tests":"378,407",
    "Tests\/  1M pop ":"119,936",
    "Source":"[1]\u00a0[2]",
    "Projections":"[projections]"
  },
  "Mississippi":{
    "Total Cases":"36,680",
    "New Cases":0,
    "Total Deaths":"1,250",
    "New Deaths":0,
    "Active Cases":"9,498",
    "Tot Cases\/ 1M pop":"12,325",
    "Deaths\/ 1M pop":"420",
    "Total Tests":"356,963",
    "Tests\/  1M pop ":"119,941",
    "Source":"[1]\u00a0[2]",
    "Projections":"[projections]"
  },
  "Wisconsin":{
    "Total Cases":"36,942",
    "New Cases":0,
    "Total Deaths":"821",
    "New Deaths":0,
    "Active Cases":"7,451",
    "Tot Cases\/ 1M pop":"6,345",
    "Deaths\/ 1M pop":"141",
    "Total Tests":"696,421",
    "Tests\/  1M pop ":"119,610",
    "Source":"[1]\u00a0[2]\u00a0[3]\u00a0[4]\u00a0[5]\u00a0[6]",
    "Projections":"[projections]"
  },
  "Colorado":{
    "Total Cases":"37,242",
    "New Cases":0,
    "Total Deaths":"1,727",
    "New Deaths":0,
    "Active Cases":"22,944",
    "Tot Cases\/ 1M pop":"6,467",
    "Deaths\/ 1M pop":"300",
    "Total Tests":"401,942",
    "Tests\/  1M pop ":"69,797",
    "Source":"[1]",
    "Projections":"[projections]"
  },
  "West Virginia":{
    "Total Cases":"4,313",
    "New Cases":0,
    "Total Deaths":"97",
    "New Deaths":0,
    "Active Cases":"1,333",
    "Tot Cases\/ 1M pop":"2,407",
    "Deaths\/ 1M pop":"54",
    "Total Tests":"211,006",
    "Tests\/  1M pop ":"117,739",
    "Source":"[1]",
    "Projections":"[projections]"
  },
  "North Dakota":{
    "Total Cases":"4,442",
    "New Cases":0,
    "Total Deaths":"87",
    "New Deaths":0,
    "Active Cases":"702",
    "Tot Cases\/ 1M pop":"5,829",
    "Deaths\/ 1M pop":"114",
    "Total Tests":"123,878",
    "Tests\/  1M pop ":"162,556",
    "Source":"[1]\u00a0[2]",
    "Projections":"[projections]"
  },
  "Washington":{
    "Total Cases":"42,741",
    "New Cases":0,
    "Total Deaths":"1,438",
    "New Deaths":0,
    "Active Cases":"27,639",
    "Tot Cases\/ 1M pop":"5,613",
    "Deaths\/ 1M pop":"189",
    "Total Tests":"686,005",
    "Tests\/  1M pop ":"90,087",
    "Source":"[view by county]\u00a0[1]",
    "Projections":"[projections]"
  },
  "Minnesota":{
    "Total Cases":"42,772",
    "New Cases":0,
    "Total Deaths":"1,542",
    "New Deaths":0,
    "Active Cases":"4,031",
    "Tot Cases\/ 1M pop":"7,584",
    "Deaths\/ 1M pop":"273",
    "Total Tests":"768,989",
    "Tests\/  1M pop ":"136,354",
    "Source":"[1]\u00a0[2]",
    "Projections":"[projections]"
  },
  "New York":{
    "Total Cases":"428,303",
    "New Cases":0,
    "Total Deaths":"32,445",
    "New Deaths":0,
    "Active Cases":"209,034",
    "Tot Cases\/ 1M pop":"22,017",
    "Deaths\/ 1M pop":"1,668",
    "Total Tests":"4,724,882",
    "Tests\/  1M pop ":"242,880",
    "Source":"[view by county]\u00a0[1]\u00a0[2]\u00a0[3]",
    "Projections":"[projections]"
  },
  "Connecticut":{
    "Total Cases":"47,510",
    "New Cases":0,
    "Total Deaths":"4,371",
    "New Deaths":0,
    "Active Cases":"26,254",
    "Tot Cases\/ 1M pop":"13,326",
    "Deaths\/ 1M pop":"1,226",
    "Total Tests":"587,331",
    "Tests\/  1M pop ":"164,736",
    "Source":"[1]\u00a0[2]",
    "Projections":"[projections]"
  },
  "Indiana":{
    "Total Cases":"52,037",
    "New Cases":0,
    "Total Deaths":"2,762",
    "New Deaths":0,
    "Active Cases":"10,361",
    "Tot Cases\/ 1M pop":"7,730",
    "Deaths\/ 1M pop":"410",
    "Total Tests":"570,409",
    "Tests\/  1M pop ":"84,728",
    "Source":"[1]\u00a0[2]",
    "Projections":"[projections]"
  },
  "Alabama":{
    "Total Cases":"55,545",
    "New Cases":0,
    "Total Deaths":"1,124",
    "New Deaths":0,
    "Active Cases":"28,638",
    "Tot Cases\/ 1M pop":"11,328",
    "Deaths\/ 1M pop":"229",
    "Total Tests":"518,827",
    "Tests\/  1M pop ":"105,814",
    "Source":"[1]",
    "Projections":"[projections]"
  },
  "South Carolina":{
    "Total Cases":"58,168",
    "New Cases":0,
    "Total Deaths":"972",
    "New Deaths":0,
    "Active Cases":"36,240",
    "Tot Cases\/ 1M pop":"11,298",
    "Deaths\/ 1M pop":"189",
    "Total Tests":"553,515",
    "Tests\/  1M pop ":"107,505",
    "Source":"[1]\u00a0[2]",
    "Projections":"[projections]"
  },
  "New Hampshire":{
    "Total Cases":"6,068",
    "New Cases":0,
    "Total Deaths":"391",
    "New Deaths":0,
    "Active Cases":"621",
    "Tot Cases\/ 1M pop":"4,463",
    "Deaths\/ 1M pop":"288",
    "Total Tests":"157,666",
    "Tests\/  1M pop ":"115,956",
    "Source":"[1]",
    "Projections":"[projections]"
  },
  "Tennessee":{
    "Total Cases":"65,274",
    "New Cases":0,
    "Total Deaths":"749",
    "New Deaths":0,
    "Active Cases":"27,529",
    "Tot Cases\/ 1M pop":"9,558",
    "Deaths\/ 1M pop":"110",
    "Total Tests":"1,053,424",
    "Tests\/  1M pop ":"154,254",
    "Source":"[1]\u00a0[2]\u00a0[3]",
    "Projections":"[projections]"
  },
  "Ohio":{
    "Total Cases":"66,891",
    "New Cases":0,
    "Total Deaths":"3,069",
    "New Deaths":0,
    "Active Cases":"18,628",
    "Tot Cases\/ 1M pop":"5,723",
    "Deaths\/ 1M pop":"263",
    "Total Tests":"1,020,811",
    "Tests\/  1M pop ":"87,330",
    "Source":"[view by county]\u00a0[1]\u00a0[2]\u00a0[3]",
    "Projections":"[projections]"
  },
  "South Dakota":{
    "Total Cases":"7,524",
    "New Cases":0,
    "Total Deaths":"109",
    "New Deaths":0,
    "Active Cases":"872",
    "Tot Cases\/ 1M pop":"8,505",
    "Deaths\/ 1M pop":"123",
    "Total Tests":"91,378",
    "Tests\/  1M pop ":"103,292",
    "Source":"[1]",
    "Projections":"[projections]"
  },
  "Virginia":{
    "Total Cases":"71,642",
    "New Cases":0,
    "Total Deaths":"1,968",
    "New Deaths":0,
    "Active Cases":"60,344",
    "Tot Cases\/ 1M pop":"8,393",
    "Deaths\/ 1M pop":"231",
    "Total Tests":"895,868",
    "Tests\/  1M pop ":"104,958",
    "Source":"[1]\u00a0[2]",
    "Projections":"[projections]"
  },
  "Maryland":{
    "Total Cases":"73,527",
    "New Cases":0,
    "Total Deaths":"3,325",
    "New Deaths":0,
    "Active Cases":"64,972",
    "Tot Cases\/ 1M pop":"12,162",
    "Deaths\/ 1M pop":"550",
    "Total Tests":"818,993",
    "Tests\/  1M pop ":"135,467",
    "Source":"[1]",
    "Projections":"[projections]"
  },
  "Michigan":{
    "Total Cases":"77,198",
    "New Cases":0,
    "Total Deaths":"6,321",
    "New Deaths":0,
    "Active Cases":"18,036",
    "Tot Cases\/ 1M pop":"7,730",
    "Deaths\/ 1M pop":"633",
    "Total Tests":"1,517,856",
    "Tests\/  1M pop ":"151,985",
    "Source":"[1]\u00a0[2]\u00a0[3]\u00a0[4]",
    "Projections":"[projections]"
  },
  "Louisiana":{
    "Total Cases":"79,827",
    "New Cases":0,
    "Total Deaths":"3,428",
    "New Deaths":0,
    "Active Cases":"30,065",
    "Tot Cases\/ 1M pop":"17,172",
    "Deaths\/ 1M pop":"737",
    "Total Tests":"953,426",
    "Tests\/  1M pop ":"205,091",
    "Source":"[view by county]\u00a0[1]",
    "Projections":"[projections]"
  },
  "North Carolina":{
    "Total Cases":"87,729",
    "New Cases":0,
    "Total Deaths":"1,551",
    "New Deaths":0,
    "Active Cases":"30,860",
    "Tot Cases\/ 1M pop":"8,365",
    "Deaths\/ 1M pop":"148",
    "Total Tests":"1,220,486",
    "Tests\/  1M pop ":"116,369",
    "Source":"[1]\u00a0[2]\u00a0[3]",
    "Projections":"[projections]"
  }
}